{
 "monthly": [
  {
   "path": "/articles/20260210a/",
   "pv": "12403",
   "title": "ログ設計ガイドラインを公開しました | フューチャー技術ブログ"
  },
  {
   "path": "/articles/20260129a/",
   "pv": "3658",
   "title": "Go 1.26で go fix が面白くなった | フューチャー技術ブログ"
  },
  {
   "path": "/articles/20260123a/",
   "pv": "3444",
   "title": "アーキテクチャガイドライン振り返り（2025年）～15本を作成してみてどうだったか～ | フューチャー技術ブログ"
  },
  {
   "path": "/",
   "pv": "2900",
   "title": "フューチャー技術ブログ"
  },
  {
   "path": "/articles/20260122a/",
   "pv": "2646",
   "title": "ソフトスキルガイドラインを公開しました | フューチャー技術ブログ"
  },
  {
   "path": "/articles/20260127a/",
   "pv": "2508",
   "title": "Go 1.26連載：インデックス＋SIMD | フューチャー技術ブログ"
  },
  {
   "path": "/articles/20260130a/",
   "pv": "2459",
   "title": "Go 1.26の新GC「Green Tea（緑茶）」解説 | フューチャー技術ブログ"
  },
  {
   "path": "/articles/20260217a/",
   "pv": "2005",
   "title": "今なぜ「アルゴリズム」を学ぶのか？ —— Software Design2026年1月号への寄稿によせて | フューチャー技術ブログ"
  },
  {
   "path": "/articles/20240415a/",
   "pv": "1607",
   "title": "VSCodeでGitLensを使う | フューチャー技術ブログ"
  },
  {
   "path": "/articles/20260216a/",
   "pv": "1156",
   "title": "アーキテクチャガイドライン公開スケジュール（2026年） | フューチャー技術ブログ"
  },
  {
   "path": "/articles/20241113a/",
   "pv": "1100",
   "title": "PostgreSQLで連番を自動生成するIDENTITY列。SERIALとどちらを使うべきか | フューチャー技術ブログ"
  },
  {
   "path": "/articles/20260203a/",
   "pv": "1006",
   "title": "Go1.26 リリース連載 runtime/secret (experimental) | フューチャー技術ブログ"
  },
  {
   "path": "/articles/20260202a/",
   "pv": "864",
   "title": "Go1.26リリース連載：newプリミティブの拡張 | フューチャー技術ブログ"
  },
  {
   "path": "/articles/20260128a/",
   "pv": "833",
   "title": "Go 1.26 リリース連載 Goroutine Leak Profiles | フューチャー技術ブログ"
  },
  {
   "path": "/articles/20240726a/",
   "pv": "745",
   "title": "2024年版のDockerfileの考え方＆書き方 | フューチャー技術ブログ"
  },
  {
   "path": "/articles/20200821/",
   "pv": "642",
   "title": "エンジニアが最低限理解しておくべきOSSライセンスの基礎知識 | フューチャー技術ブログ"
  },
  {
   "path": "/articles/20231101a/",
   "pv": "551",
   "title": "設計ドキュメント腐る問題、Git管理で運用してみた結果 | フューチャー技術ブログ"
  },
  {
   "path": "/articles/20230216a/",
   "pv": "548",
   "title": "Mac 慣れした私に Windows が支給されたので、まず設定したこと | フューチャー技術ブログ"
  },
  {
   "path": "/articles/20200116/",
   "pv": "505",
   "title": "実践Drawio | フューチャー技術ブログ"
  },
  {
   "path": "/articles/20260213a/",
   "pv": "493",
   "title": "2026年2月版: Dev Containersでプチはまり(Node.js 24とPostgreSQL 18とプロキシ) | フューチャー技術ブログ"
  },
  {
   "path": "/articles/20251212a/",
   "pv": "480",
   "title": "AWS設計ガイドラインを公開しました | フューチャー技術ブログ"
  },
  {
   "path": "/articles/20220922a/",
   "pv": "458",
   "title": "AGPLを理解する: もっとも誤解されたライセンス | フューチャー技術ブログ"
  },
  {
   "path": "/articles/20250905a/",
   "pv": "421",
   "title": "Mermaid図の調整ツールで図をさらに見やすく！〜現場の課題を解決する自作ツール〜 | フューチャー技術ブログ"
  },
  {
   "path": "/articles/20260120a/",
   "pv": "418",
   "title": "なぜ日本語入力と相性の悪いWebサイトができてしまうのか | フューチャー技術ブログ"
  },
  {
   "path": "/articles/20260205a/",
   "pv": "415",
   "title": "Go 1.26で変わるcgoの高速化 〜ランタイム刷新がもたらす30%の高速化とその舞台裏〜 | フューチャー技術ブログ"
  },
  {
   "path": "/articles/20250509a/",
   "pv": "408",
   "title": "Goのテストをはじめてみよう（2025年版） | フューチャー技術ブログ"
  },
  {
   "path": "/articles/20211201a/",
   "pv": "402",
   "title": "巡回セールスマン問題(TSP)の基本的な解き方(ILS) | フューチャー技術ブログ"
  },
  {
   "path": "/articles/20200810/",
   "pv": "377",
   "title": "自動売買ツールを自作してみよう | フューチャー技術ブログ"
  },
  {
   "path": "/articles/",
   "pv": "364",
   "title": "Archives | フューチャー技術ブログ"
  },
  {
   "path": "/articles/20220530a/",
   "pv": "326",
   "title": "【エネルギー業界】LPガス基礎part2 供給設備編 | フューチャー技術ブログ"
  },
  {
   "path": "/articles/20250417a/",
   "pv": "315",
   "title": "GitLabのレビューにPR-Agentを組み込んでみた | フューチャー技術ブログ"
  },
  {
   "path": "/articles/20240705a/",
   "pv": "309",
   "title": "署名付きURLを利用したファイルアップロードWeb API設計の勘所 | フューチャー技術ブログ"
  },
  {
   "path": "/articles/20260209a/",
   "pv": "306",
   "title": "新規事業開発にて「ITやAIは目的ではなく手段である」と再確認した話 | フューチャー技術ブログ"
  },
  {
   "path": "/articles/20251117a/",
   "pv": "305",
   "title": "AI暴走を防ごう！AIエージェントのガードレールの作り方を考えてみよう | フューチャー技術ブログ"
  },
  {
   "path": "/articles/20240626b/",
   "pv": "298",
   "title": "社会人からはじめる競技プログラミング | フューチャー技術ブログ"
  },
  {
   "path": "/articles/20231128a/",
   "pv": "293",
   "title": "data-testidはいつ使うべきか？そもそも使うべきなのか？ | フューチャー技術ブログ"
  },
  {
   "path": "/articles/20240611a/",
   "pv": "290",
   "title": "Gitのブランチの役割を考える | フューチャー技術ブログ"
  },
  {
   "path": "/articles/20210331/",
   "pv": "281",
   "title": "今さらながらfindパイセンについてまとめてみた | フューチャー技術ブログ"
  },
  {
   "path": "/articles/20231124a/",
   "pv": "271",
   "title": "学習のSHA 〜ハッシュ関数の基本と安全性について学ぶ〜 | フューチャー技術ブログ"
  },
  {
   "path": "/articles/20240620a/",
   "pv": "269",
   "title": "個人的docker composeおすすめtips 9選 | フューチャー技術ブログ"
  },
  {
   "path": "/articles/20210204/",
   "pv": "254",
   "title": "JP1ジョブ設計のポイント（初級） | フューチャー技術ブログ"
  },
  {
   "path": "/articles/20200828/",
   "pv": "246",
   "title": "チームで推奨するVSCode拡張機能を共有するtips | フューチャー技術ブログ"
  },
  {
   "path": "/articles/20250911a/",
   "pv": "246",
   "title": "Webフロントエンド設計ガイドラインを公開しました | フューチャー技術ブログ"
  },
  {
   "path": "/articles/20250425a/",
   "pv": "237",
   "title": "VS CodeによるiOSアプリ開発入門〜ビルド＆ラン〜 | フューチャー技術ブログ"
  },
  {
   "path": "/articles/20220628a/",
   "pv": "233",
   "title": "資料作成のポイント（定例、課題解決用） | フューチャー技術ブログ"
  },
  {
   "path": "/articles/20230310a/",
   "pv": "232",
   "title": "本当は怖い、逆コンウェイ戦略 | フューチャー技術ブログ"
  },
  {
   "path": "/articles/20240419a/",
   "pv": "231",
   "title": "CI/CD初心者のためのJenkins入門 | フューチャー技術ブログ"
  },
  {
   "path": "/articles/20260212a/",
   "pv": "231",
   "title": "API費用8ドル。「ホリエモンAI選挙」の分析フローをDifyで一部再現してみた ‐ マルチAIエージェント実装ガイド | フューチャー技術ブログ"
  },
  {
   "path": "/articles/20160721/",
   "pv": "228",
   "title": "これさえあればシステム構成図がだいたい描けるアイコンセットを公開します！ | フューチャー技術ブログ"
  },
  {
   "path": "/articles/20250602a/",
   "pv": "228",
   "title": "FastAPI on Dockerがかなりシンプルになった(2025年版) | フューチャー技術ブログ"
  }
 ],
 "weekly": [
  {
   "path": "/articles/20260210a/",
   "pv": "3876",
   "title": "ログ設計ガイドラインを公開しました | フューチャー技術ブログ"
  },
  {
   "path": "/articles/20260217a/",
   "pv": "2005",
   "title": "今なぜ「アルゴリズム」を学ぶのか？ —— Software Design2026年1月号への寄稿によせて | フューチャー技術ブログ"
  },
  {
   "path": "/articles/20260216a/",
   "pv": "1156",
   "title": "アーキテクチャガイドライン公開スケジュール（2026年） | フューチャー技術ブログ"
  },
  {
   "path": "/",
   "pv": "726",
   "title": "フューチャー技術ブログ"
  },
  {
   "path": "/articles/20260213a/",
   "pv": "493",
   "title": "2026年2月版: Dev Containersでプチはまり(Node.js 24とPostgreSQL 18とプロキシ) | フューチャー技術ブログ"
  },
  {
   "path": "/articles/20260129a/",
   "pv": "418",
   "title": "Go 1.26で go fix が面白くなった | フューチャー技術ブログ"
  },
  {
   "path": "/articles/20240415a/",
   "pv": "372",
   "title": "VSCodeでGitLensを使う | フューチャー技術ブログ"
  },
  {
   "path": "/articles/20241113a/",
   "pv": "279",
   "title": "PostgreSQLで連番を自動生成するIDENTITY列。SERIALとどちらを使うべきか | フューチャー技術ブログ"
  },
  {
   "path": "/articles/20260212a/",
   "pv": "231",
   "title": "API費用8ドル。「ホリエモンAI選挙」の分析フローをDifyで一部再現してみた ‐ マルチAIエージェント実装ガイド | フューチャー技術ブログ"
  },
  {
   "path": "/articles/20260123a/",
   "pv": "204",
   "title": "アーキテクチャガイドライン振り返り（2025年）～15本を作成してみてどうだったか～ | フューチャー技術ブログ"
  },
  {
   "path": "/articles/20240726a/",
   "pv": "167",
   "title": "2024年版のDockerfileの考え方＆書き方 | フューチャー技術ブログ"
  },
  {
   "path": "/articles/20260127a/",
   "pv": "153",
   "title": "Go 1.26連載：インデックス＋SIMD | フューチャー技術ブログ"
  },
  {
   "path": "/articles/20231101a/",
   "pv": "132",
   "title": "設計ドキュメント腐る問題、Git管理で運用してみた結果 | フューチャー技術ブログ"
  },
  {
   "path": "/articles/20230216a/",
   "pv": "131",
   "title": "Mac 慣れした私に Windows が支給されたので、まず設定したこと | フューチャー技術ブログ"
  },
  {
   "path": "/articles/20260202a/",
   "pv": "119",
   "title": "Go1.26リリース連載：newプリミティブの拡張 | フューチャー技術ブログ"
  },
  {
   "path": "/articles/20251212a/",
   "pv": "110",
   "title": "AWS設計ガイドラインを公開しました | フューチャー技術ブログ"
  },
  {
   "path": "/articles/20260130a/",
   "pv": "110",
   "title": "Go 1.26の新GC「Green Tea（緑茶）」解説 | フューチャー技術ブログ"
  },
  {
   "path": "/articles/20260122a/",
   "pv": "106",
   "title": "ソフトスキルガイドラインを公開しました | フューチャー技術ブログ"
  },
  {
   "path": "/articles/",
   "pv": "105",
   "title": "Archives | フューチャー技術ブログ"
  },
  {
   "path": "/articles/20200821/",
   "pv": "105",
   "title": "エンジニアが最低限理解しておくべきOSSライセンスの基礎知識 | フューチャー技術ブログ"
  },
  {
   "path": "/articles/20200116/",
   "pv": "99",
   "title": "実践Drawio | フューチャー技術ブログ"
  },
  {
   "path": "/articles/20250509a/",
   "pv": "98",
   "title": "Goのテストをはじめてみよう（2025年版） | フューチャー技術ブログ"
  },
  {
   "path": "/articles/20200810/",
   "pv": "97",
   "title": "自動売買ツールを自作してみよう | フューチャー技術ブログ"
  },
  {
   "path": "/articles/20251117a/",
   "pv": "95",
   "title": "AI暴走を防ごう！AIエージェントのガードレールの作り方を考えてみよう | フューチャー技術ブログ"
  },
  {
   "path": "/articles/20240705a/",
   "pv": "91",
   "title": "署名付きURLを利用したファイルアップロードWeb API設計の勘所 | フューチャー技術ブログ"
  },
  {
   "path": "/articles/20250905a/",
   "pv": "91",
   "title": "Mermaid図の調整ツールで図をさらに見やすく！〜現場の課題を解決する自作ツール〜 | フューチャー技術ブログ"
  },
  {
   "path": "/articles/20250417a/",
   "pv": "90",
   "title": "GitLabのレビューにPR-Agentを組み込んでみた | フューチャー技術ブログ"
  },
  {
   "path": "/articles/20260209a/",
   "pv": "89",
   "title": "新規事業開発にて「ITやAIは目的ではなく手段である」と再確認した話 | フューチャー技術ブログ"
  },
  {
   "path": "/articles/20220530a/",
   "pv": "81",
   "title": "【エネルギー業界】LPガス基礎part2 供給設備編 | フューチャー技術ブログ"
  },
  {
   "path": "/articles/20220922a/",
   "pv": "78",
   "title": "AGPLを理解する: もっとも誤解されたライセンス | フューチャー技術ブログ"
  },
  {
   "path": "/articles/20260205a/",
   "pv": "78",
   "title": "Go 1.26で変わるcgoの高速化 〜ランタイム刷新がもたらす30%の高速化とその舞台裏〜 | フューチャー技術ブログ"
  },
  {
   "path": "/articles/20231128a/",
   "pv": "76",
   "title": "data-testidはいつ使うべきか？そもそも使うべきなのか？ | フューチャー技術ブログ"
  },
  {
   "path": "/articles/20240611a/",
   "pv": "71",
   "title": "Gitのブランチの役割を考える | フューチャー技術ブログ"
  },
  {
   "path": "/articles/20201020/",
   "pv": "67",
   "title": "ProxyとDockerと新人社員と時々わたし | フューチャー技術ブログ"
  },
  {
   "path": "/articles/20210401/",
   "pv": "66",
   "title": "declare使ってBashで配列と連想配列 | フューチャー技術ブログ"
  },
  {
   "path": "/articles/20211201a/",
   "pv": "62",
   "title": "巡回セールスマン問題(TSP)の基本的な解き方(ILS) | フューチャー技術ブログ"
  },
  {
   "path": "/articles/20220713a/",
   "pv": "62",
   "title": "【エネルギー業界】LPガス基礎part4 バルク配送入門 | フューチャー技術ブログ"
  },
  {
   "path": "/articles/20240603a/",
   "pv": "62",
   "title": "Cloudflare R2 + NextCloudで作る自分専用クラウドストレージのススメ | フューチャー技術ブログ"
  },
  {
   "path": "/articles/20210204/",
   "pv": "58",
   "title": "JP1ジョブ設計のポイント（初級） | フューチャー技術ブログ"
  },
  {
   "path": "/articles/20221012a/",
   "pv": "58",
   "title": "OAuth の仕組みを理解しながらクライアントを実装してみる | フューチャー技術ブログ"
  },
  {
   "path": "/articles/20240620a/",
   "pv": "57",
   "title": "個人的docker composeおすすめtips 9選 | フューチャー技術ブログ"
  },
  {
   "path": "/articles/20230310a/",
   "pv": "56",
   "title": "本当は怖い、逆コンウェイ戦略 | フューチャー技術ブログ"
  },
  {
   "path": "/articles/20250425a/",
   "pv": "55",
   "title": "VS CodeによるiOSアプリ開発入門〜ビルド＆ラン〜 | フューチャー技術ブログ"
  },
  {
   "path": "/articles/20260203a/",
   "pv": "55",
   "title": "Go1.26 リリース連載 runtime/secret (experimental) | フューチャー技術ブログ"
  },
  {
   "path": "/articles/20160721/",
   "pv": "54",
   "title": "これさえあればシステム構成図がだいたい描けるアイコンセットを公開します！ | フューチャー技術ブログ"
  },
  {
   "path": "/articles/20200828/",
   "pv": "54",
   "title": "チームで推奨するVSCode拡張機能を共有するtips | フューチャー技術ブログ"
  },
  {
   "path": "/articles/20250911a/",
   "pv": "54",
   "title": "Webフロントエンド設計ガイドラインを公開しました | フューチャー技術ブログ"
  },
  {
   "path": "/articles/20210705a/",
   "pv": "53",
   "title": "キューとリングバッファについてやさしい言葉で解説してみる | フューチャー技術ブログ"
  },
  {
   "path": "/articles/20250414a/",
   "pv": "51",
   "title": "初めてのPostman | フューチャー技術ブログ"
  },
  {
   "path": "/articles/20251218a/",
   "pv": "51",
   "title": "Software Design 2026年1月号のアルゴリズム特集に寄稿したお話 | フューチャー技術ブログ"
  }
 ],
 "yearly": [
  {
   "path": "/",
   "pv": "31639",
   "title": "フューチャー技術ブログ"
  },
  {
   "path": "/articles/20250324a/",
   "pv": "14936",
   "title": "【理論編】HTTPS通信の中身を見て、どのようにしてセキュアな通信が確立されるかを理解する | フューチャー技術ブログ"
  },
  {
   "path": "/articles/20241113a/",
   "pv": "14488",
   "title": "PostgreSQLで連番を自動生成するIDENTITY列。SERIALとどちらを使うべきか | フューチャー技術ブログ"
  },
  {
   "path": "/articles/20240726a/",
   "pv": "14053",
   "title": "2024年版のDockerfileの考え方＆書き方 | フューチャー技術ブログ"
  },
  {
   "path": "/articles/20240415a/",
   "pv": "13683",
   "title": "VSCodeでGitLensを使う | フューチャー技術ブログ"
  },
  {
   "path": "/articles/20200821/",
   "pv": "12403",
   "title": "エンジニアが最低限理解しておくべきOSSライセンスの基礎知識 | フューチャー技術ブログ"
  },
  {
   "path": "/articles/20260210a/",
   "pv": "12403",
   "title": "ログ設計ガイドラインを公開しました | フューチャー技術ブログ"
  },
  {
   "path": "/articles/20250602a/",
   "pv": "11599",
   "title": "FastAPI on Dockerがかなりシンプルになった(2025年版) | フューチャー技術ブログ"
  },
  {
   "path": "/articles/20250911a/",
   "pv": "10652",
   "title": "Webフロントエンド設計ガイドラインを公開しました | フューチャー技術ブログ"
  },
  {
   "path": "/articles/20251106a/",
   "pv": "10478",
   "title": "データベースと向き合う決意をしてから3年たった | フューチャー技術ブログ"
  },
  {
   "path": "/articles/20251212a/",
   "pv": "9743",
   "title": "AWS設計ガイドラインを公開しました | フューチャー技術ブログ"
  },
  {
   "path": "/articles/20251107a/",
   "pv": "9260",
   "title": "なぜアーキチームは設計や実装のパターンを絞りたいか？ 背景にある思考と技術選定のジレンマ | フューチャー技術ブログ"
  },
  {
   "path": "/articles/20250530a/",
   "pv": "8898",
   "title": "PostgreSQL設計ガイドラインのご紹介 | フューチャー技術ブログ"
  },
  {
   "path": "/articles/20230216a/",
   "pv": "7612",
   "title": "Mac 慣れした私に Windows が支給されたので、まず設定したこと | フューチャー技術ブログ"
  },
  {
   "path": "/articles/20231101a/",
   "pv": "7527",
   "title": "設計ドキュメント腐る問題、Git管理で運用してみた結果 | フューチャー技術ブログ"
  },
  {
   "path": "/articles/20250918a/",
   "pv": "7074",
   "title": "バッチ設計ガイドラインを公開しました | フューチャー技術ブログ"
  },
  {
   "path": "/articles/20250829a/",
   "pv": "7001",
   "title": "PostgreSQLの全文検索機能を試してみる | フューチャー技術ブログ"
  },
  {
   "path": "/articles/20250513b/",
   "pv": "6998",
   "title": "Web API設計ガイドラインを公開しました | フューチャー技術ブログ"
  },
  {
   "path": "/articles/20250728a/",
   "pv": "6869",
   "title": "GoogleカレンダーをGeminiアプリの外部記憶装置として活用する | フューチャー技術ブログ"
  },
  {
   "path": "/articles/20250409a/",
   "pv": "6509",
   "title": "Terraform設計ガイドラインを公開しました | フューチャー技術ブログ"
  },
  {
   "path": "/articles/20200116/",
   "pv": "6300",
   "title": "実践Drawio | フューチャー技術ブログ"
  },
  {
   "path": "/articles/20250509a/",
   "pv": "6019",
   "title": "Goのテストをはじめてみよう（2025年版） | フューチャー技術ブログ"
  },
  {
   "path": "/articles/20220922a/",
   "pv": "5867",
   "title": "AGPLを理解する: もっとも誤解されたライセンス | フューチャー技術ブログ"
  },
  {
   "path": "/articles/20251014a/",
   "pv": "5810",
   "title": "PostgreSQL 18の新機能「B-treeインデックスのスキップスキャン」 | フューチャー技術ブログ"
  },
  {
   "path": "/articles/20250428a/",
   "pv": "5486",
   "title": "CursorによるAI駆動開発入門 | フューチャー技術ブログ"
  },
  {
   "path": "/articles/20211201a/",
   "pv": "5046",
   "title": "巡回セールスマン問題(TSP)の基本的な解き方(ILS) | フューチャー技術ブログ"
  },
  {
   "path": "/articles/20240419a/",
   "pv": "4941",
   "title": "CI/CD初心者のためのJenkins入門 | フューチャー技術ブログ"
  },
  {
   "path": "/articles/20220530a/",
   "pv": "4710",
   "title": "【エネルギー業界】LPガス基礎part2 供給設備編 | フューチャー技術ブログ"
  },
  {
   "path": "/articles/20251003a/",
   "pv": "4677",
   "title": "メール設計ガイドラインを公開しました | フューチャー技術ブログ"
  },
  {
   "path": "/articles/20250818a/",
   "pv": "4542",
   "title": "I/F設計ガイドラインを公開しました | フューチャー技術ブログ"
  },
  {
   "path": "/articles/20250610a/",
   "pv": "4340",
   "title": "macOS 26でLinuxコンテナのネイティブサポートが来る | フューチャー技術ブログ"
  },
  {
   "path": "/articles/20250827a/",
   "pv": "4197",
   "title": "リスクアセスメント　ーリスクの可視化から意思決定までー | フューチャー技術ブログ"
  },
  {
   "path": "/articles/20210621a/",
   "pv": "4159",
   "title": "どうしてHTML5が廃止されたのか | フューチャー技術ブログ"
  },
  {
   "path": "/articles/20211026a/",
   "pv": "4032",
   "title": "AWS利用時に read: connection reset by peer が出たときのリトライ検討 | フューチャー技術ブログ"
  },
  {
   "path": "/articles/20200828/",
   "pv": "3993",
   "title": "チームで推奨するVSCode拡張機能を共有するtips | フューチャー技術ブログ"
  },
  {
   "path": "/articles/20231128a/",
   "pv": "3947",
   "title": "data-testidはいつ使うべきか？そもそも使うべきなのか？ | フューチャー技術ブログ"
  },
  {
   "path": "/articles/20240705a/",
   "pv": "3939",
   "title": "署名付きURLを利用したファイルアップロードWeb API設計の勘所 | フューチャー技術ブログ"
  },
  {
   "path": "/articles/20250604a/",
   "pv": "3935",
   "title": "GitHub 標準の Annotation を活用してレビューを可視化する | フューチャー技術ブログ"
  },
  {
   "path": "/articles/20220628a/",
   "pv": "3881",
   "title": "資料作成のポイント（定例、課題解決用） | フューチャー技術ブログ"
  },
  {
   "path": "/articles/20250417a/",
   "pv": "3802",
   "title": "GitLabのレビューにPR-Agentを組み込んでみた | フューチャー技術ブログ"
  },
  {
   "path": "/articles/20250620a/",
   "pv": "3744",
   "title": "Gemma3 + Unsloth + GitLab CI/CDで構築する完全オンプレミスAIコードレビュー環境 | フューチャー技術ブログ"
  },
  {
   "path": "/articles/20250729a/",
   "pv": "3676",
   "title": "伸びる人の条件についてSlackで話した | フューチャー技術ブログ"
  },
  {
   "path": "/articles/20260129a/",
   "pv": "3658",
   "title": "Go 1.26で go fix が面白くなった | フューチャー技術ブログ"
  },
  {
   "path": "/articles/20250708a/",
   "pv": "3556",
   "title": "プロンプトエンジニアリングから逆算して考える、エンジニアのスキルアップ | フューチャー技術ブログ"
  },
  {
   "path": "/articles/20260123a/",
   "pv": "3444",
   "title": "アーキテクチャガイドライン振り返り（2025年）～15本を作成してみてどうだったか～ | フューチャー技術ブログ"
  },
  {
   "path": "/articles/20211028b/",
   "pv": "3415",
   "title": "OpenAPIにおけるundefinedとnullの設計 | フューチャー技術ブログ"
  },
  {
   "path": "/articles/20250314a/",
   "pv": "3405",
   "title": "Tailwind CSSのドキュメントから見えてくる使い方とCSS設計のヒント | フューチャー技術ブログ"
  },
  {
   "path": "/articles/20251007a/",
   "pv": "3400",
   "title": "会議の後に「ラップアップ」を入れてチームを強くする | フューチャー技術ブログ"
  },
  {
   "path": "/articles/20250722a/",
   "pv": "3385",
   "title": "生成AIとはじめる、バックオフィス業務改革 ～Geminiの有効な使い方～ | フューチャー技術ブログ"
  },
  {
   "path": "/articles/20250603b/",
   "pv": "3367",
   "title": "Dokployで自宅PaaSを構築する | フューチャー技術ブログ"
  }
 ]
}
