{
 "monthly": [
  {
   "path": "/articles/20240726a/",
   "pv": "7879",
   "title": "2024年版のDockerfileの考え方＆書き方 | フューチャー技術ブログ"
  },
  {
   "path": "/",
   "pv": "2111",
   "title": "フューチャー技術ブログ"
  },
  {
   "path": "/articles/20200821/",
   "pv": "1528",
   "title": "エンジニアが最低限理解しておくべきOSSライセンスの基礎知識 | フューチャー技術ブログ"
  },
  {
   "path": "/articles/20211026a/",
   "pv": "1501",
   "title": "AWS利用時に read: connection reset by peer が出たときのリトライ検討 | フューチャー技術ブログ"
  },
  {
   "path": "/articles/20220922a/",
   "pv": "1097",
   "title": "AGPLを理解する: もっとも誤解されたライセンス | フューチャー技術ブログ"
  },
  {
   "path": "/articles/20240716a/",
   "pv": "1050",
   "title": "Go 1.23リリース連載始まります＆timeパッケージ | フューチャー技術ブログ"
  },
  {
   "path": "/articles/20230216a/",
   "pv": "967",
   "title": "Mac 慣れした私に Windows が支給されたので、まず設定したこと | フューチャー技術ブログ"
  },
  {
   "path": "/articles/20210621a/",
   "pv": "952",
   "title": "どうしてHTML5が廃止されたのか | フューチャー技術ブログ"
  },
  {
   "path": "/articles/20201223/",
   "pv": "842",
   "title": "2021年版Pythonの型ヒントの書き方 (for Python 3.9) | フューチャー技術ブログ"
  },
  {
   "path": "/articles/20240620a/",
   "pv": "792",
   "title": "個人的docker composeおすすめtips 9選 | フューチャー技術ブログ"
  },
  {
   "path": "/articles/20240718a/",
   "pv": "774",
   "title": "Go 1.23リリース連載 range over funcとiterパッケージ | フューチャー技術ブログ"
  },
  {
   "path": "/articles/20240415a/",
   "pv": "663",
   "title": "VSCodeでGitLensを使う | フューチャー技術ブログ"
  },
  {
   "path": "/articles/20231101a/",
   "pv": "620",
   "title": "設計ドキュメント腐る問題、Git管理で運用してみた結果 | フューチャー技術ブログ"
  },
  {
   "path": "/articles/20211028b/",
   "pv": "596",
   "title": "OpenAPIにおけるundefinedとnullの設計 | フューチャー技術ブログ"
  },
  {
   "path": "/articles/20240719a/",
   "pv": "575",
   "title": "Go1.23 リリース連載 slices/maps（+ unique） | フューチャー技術ブログ"
  },
  {
   "path": "/articles/20240705a/",
   "pv": "507",
   "title": "署名付きURLを利用したファイルアップロードWeb API設計の勘所 | フューチャー技術ブログ"
  },
  {
   "path": "/articles/20221116a/",
   "pv": "495",
   "title": "Plotly.pyによるデータ可視化のすすめ | フューチャー技術ブログ"
  },
  {
   "path": "/articles/20210518a/",
   "pv": "494",
   "title": "HTTP検索条件、GETにするか？POSTにするか？ | フューチャー技術ブログ"
  },
  {
   "path": "/articles/20200810/",
   "pv": "488",
   "title": "自動売買ツールを自作してみよう | フューチャー技術ブログ"
  },
  {
   "path": "/articles/20200828/",
   "pv": "486",
   "title": "チームで推奨するVSCode拡張機能を共有するtips | フューチャー技術ブログ"
  },
  {
   "path": "/articles/20200116/",
   "pv": "470",
   "title": "実践Drawio | フューチャー技術ブログ"
  },
  {
   "path": "/articles/20200428/",
   "pv": "459",
   "title": "Vue.jsのslotの機能を初心者にわかるように解説してみた | フューチャー技術ブログ"
  },
  {
   "path": "/articles/20240819b/",
   "pv": "447",
   "title": "パーサーコンビネータをもっと身近にする | フューチャー技術ブログ"
  },
  {
   "path": "/articles/20230313a/",
   "pv": "431",
   "title": "【エネルギー業界】国家資格「高圧ガス第二種販売主任者」合格までの道のり | フューチャー技術ブログ"
  },
  {
   "path": "/articles/20220929a/",
   "pv": "416",
   "title": "AGPLが適する場所、適さない場所 | フューチャー技術ブログ"
  },
  {
   "path": "/articles/20220628a/",
   "pv": "410",
   "title": "資料作成のポイント（定例、課題解決用） | フューチャー技術ブログ"
  },
  {
   "path": "/articles/20220530a/",
   "pv": "407",
   "title": "【エネルギー業界】LPガス基礎part2 供給設備編 | フューチャー技術ブログ"
  },
  {
   "path": "/articles/20210401/",
   "pv": "403",
   "title": "declare使ってBashで配列と連想配列 | フューチャー技術ブログ"
  },
  {
   "path": "/articles/20231128a/",
   "pv": "398",
   "title": "data-testidはいつ使うべきか？そもそも使うべきなのか？ | フューチャー技術ブログ"
  },
  {
   "path": "/articles/20200513/",
   "pv": "386",
   "title": "仕事でPythonコンテナをデプロイする人向けのDockerfile (1): オールマイティ編 | フューチャー技術ブログ"
  },
  {
   "path": "/articles/20210823b/",
   "pv": "384",
   "title": "Wiresharkで通信プロトコルを見る | フューチャー技術ブログ"
  },
  {
   "path": "/articles/20211201a/",
   "pv": "383",
   "title": "巡回セールスマン問題(TSP)の基本的な解き方(ILS) | フューチャー技術ブログ"
  },
  {
   "path": "/articles/20220621a/",
   "pv": "375",
   "title": "ファイルダウンロード完全マスター | フューチャー技術ブログ"
  },
  {
   "path": "/articles/20210204/",
   "pv": "369",
   "title": "JP1ジョブ設計のポイント（初級） | フューチャー技術ブログ"
  },
  {
   "path": "/articles/20210120/",
   "pv": "357",
   "title": "Androidのビルドバリアントをイチから理解する | フューチャー技術ブログ"
  },
  {
   "path": "/articles/20210331/",
   "pv": "329",
   "title": "今さらながらfindパイセンについてまとめてみた | フューチャー技術ブログ"
  },
  {
   "path": "/articles/20221031b/",
   "pv": "329",
   "title": "バーチャルデスクトップ環境の現状と、VRの個人的な感想 | フューチャー技術ブログ"
  },
  {
   "path": "/articles/20240402a/",
   "pv": "323",
   "title": "Difyで生成AIアプリケーション入門　前編：生成AIアプリケーションをノーコードで開発 | フューチャー技術ブログ"
  },
  {
   "path": "/articles/20191107/",
   "pv": "322",
   "title": "インフラ入門vol.3(ネットワーク冗長化構成) | フューチャー技術ブログ"
  },
  {
   "path": "/articles/20221128a/",
   "pv": "315",
   "title": "業務システム開発でsqlcを導入して良かった点とハマった点 | フューチャー技術ブログ"
  },
  {
   "path": "/articles/20221118a/",
   "pv": "310",
   "title": "MSAL.jsを使ってウェブフロントエンドだけでAzureAD認証する | フューチャー技術ブログ"
  },
  {
   "path": "/articles/20211006b/",
   "pv": "296",
   "title": "AWSクラウドの耐障害性、可用性を高めるための前提知識 | フューチャー技術ブログ"
  },
  {
   "path": "/articles/20240419a/",
   "pv": "293",
   "title": "CI/CD初心者のためのJenkins入門 | フューチャー技術ブログ"
  },
  {
   "path": "/articles/20200409/",
   "pv": "285",
   "title": "スキーマファースト開発のためのOpenAPI（Swagger）設計規約 | フューチャー技術ブログ"
  },
  {
   "path": "/articles/20200601/",
   "pv": "285",
   "title": "Goのテストに入門してみよう！ | フューチャー技術ブログ"
  },
  {
   "path": "/articles/20210705a/",
   "pv": "279",
   "title": "キューとリングバッファについてやさしい言葉で解説してみる | フューチャー技術ブログ"
  },
  {
   "path": "/articles/20240829a/",
   "pv": "277",
   "title": "OpenAPIでOAuth認可周りのサーバサイドコード生成を比較 | フューチャー技術ブログ"
  },
  {
   "path": "/articles/20240611a/",
   "pv": "268",
   "title": "Gitのブランチの役割を考える | フューチャー技術ブログ"
  },
  {
   "path": "/articles/20240805a/",
   "pv": "267",
   "title": "Google Cloud Next Tokyo '24 2日目参加レポート | フューチャー技術ブログ"
  },
  {
   "path": "/articles/20210225/",
   "pv": "264",
   "title": "DynamoDBから効率的に大量のデータを取得する方法 | フューチャー技術ブログ"
  }
 ],
 "weekly": [
  {
   "path": "/articles/20240726a/",
   "pv": "1164",
   "title": "2024年版のDockerfileの考え方＆書き方 | フューチャー技術ブログ"
  },
  {
   "path": "/",
   "pv": "617",
   "title": "フューチャー技術ブログ"
  },
  {
   "path": "/articles/20220922a/",
   "pv": "494",
   "title": "AGPLを理解する: もっとも誤解されたライセンス | フューチャー技術ブログ"
  },
  {
   "path": "/articles/20200821/",
   "pv": "475",
   "title": "エンジニアが最低限理解しておくべきOSSライセンスの基礎知識 | フューチャー技術ブログ"
  },
  {
   "path": "/articles/20211026a/",
   "pv": "401",
   "title": "AWS利用時に read: connection reset by peer が出たときのリトライ検討 | フューチャー技術ブログ"
  },
  {
   "path": "/articles/20240829a/",
   "pv": "277",
   "title": "OpenAPIでOAuth認可周りのサーバサイドコード生成を比較 | フューチャー技術ブログ"
  },
  {
   "path": "/articles/20210621a/",
   "pv": "268",
   "title": "どうしてHTML5が廃止されたのか | フューチャー技術ブログ"
  },
  {
   "path": "/articles/20230216a/",
   "pv": "239",
   "title": "Mac 慣れした私に Windows が支給されたので、まず設定したこと | フューチャー技術ブログ"
  },
  {
   "path": "/articles/20240827a/",
   "pv": "233",
   "title": "Software Design 2024年9月号 Goのエラーハンドリングと向き合う ベストな設計戦略を徹底解剖を寄稿しました | フューチャー技術ブログ"
  },
  {
   "path": "/articles/20220929a/",
   "pv": "226",
   "title": "AGPLが適する場所、適さない場所 | フューチャー技術ブログ"
  },
  {
   "path": "/articles/20201223/",
   "pv": "219",
   "title": "2021年版Pythonの型ヒントの書き方 (for Python 3.9) | フューチャー技術ブログ"
  },
  {
   "path": "/articles/20240826a/",
   "pv": "216",
   "title": "人工知能学会全国大会2024で発表してきました | フューチャー技術ブログ"
  },
  {
   "path": "/articles/20240620a/",
   "pv": "192",
   "title": "個人的docker composeおすすめtips 9選 | フューチャー技術ブログ"
  },
  {
   "path": "/articles/20231101a/",
   "pv": "180",
   "title": "設計ドキュメント腐る問題、Git管理で運用してみた結果 | フューチャー技術ブログ"
  },
  {
   "path": "/articles/20240718a/",
   "pv": "178",
   "title": "Go 1.23リリース連載 range over funcとiterパッケージ | フューチャー技術ブログ"
  },
  {
   "path": "/articles/20240828a/",
   "pv": "176",
   "title": "埋め込みベクトルでSlackのカスタム絵文字を分類・検索 | フューチャー技術ブログ"
  },
  {
   "path": "/articles/20211028b/",
   "pv": "169",
   "title": "OpenAPIにおけるundefinedとnullの設計 | フューチャー技術ブログ"
  },
  {
   "path": "/articles/20240419a/",
   "pv": "167",
   "title": "CI/CD初心者のためのJenkins入門 | フューチャー技術ブログ"
  },
  {
   "path": "/articles/20240415a/",
   "pv": "166",
   "title": "VSCodeでGitLensを使う | フューチャー技術ブログ"
  },
  {
   "path": "/articles/20240716a/",
   "pv": "162",
   "title": "Go 1.23リリース連載始まります＆timeパッケージ | フューチャー技術ブログ"
  },
  {
   "path": "/articles/20221116a/",
   "pv": "146",
   "title": "Plotly.pyによるデータ可視化のすすめ | フューチャー技術ブログ"
  },
  {
   "path": "/articles/20220530a/",
   "pv": "131",
   "title": "【エネルギー業界】LPガス基礎part2 供給設備編 | フューチャー技術ブログ"
  },
  {
   "path": "/articles/20210401/",
   "pv": "130",
   "title": "declare使ってBashで配列と連想配列 | フューチャー技術ブログ"
  },
  {
   "path": "/articles/20200428/",
   "pv": "123",
   "title": "Vue.jsのslotの機能を初心者にわかるように解説してみた | フューチャー技術ブログ"
  },
  {
   "path": "/articles/20230313a/",
   "pv": "122",
   "title": "【エネルギー業界】国家資格「高圧ガス第二種販売主任者」合格までの道のり | フューチャー技術ブログ"
  },
  {
   "path": "/articles/20210518a/",
   "pv": "120",
   "title": "HTTP検索条件、GETにするか？POSTにするか？ | フューチャー技術ブログ"
  },
  {
   "path": "/articles/20231128a/",
   "pv": "120",
   "title": "data-testidはいつ使うべきか？そもそも使うべきなのか？ | フューチャー技術ブログ"
  },
  {
   "path": "/articles/20240719a/",
   "pv": "120",
   "title": "Go1.23 リリース連載 slices/maps（+ unique） | フューチャー技術ブログ"
  },
  {
   "path": "/articles/20200116/",
   "pv": "118",
   "title": "実践Drawio | フューチャー技術ブログ"
  },
  {
   "path": "/articles/20240705a/",
   "pv": "114",
   "title": "署名付きURLを利用したファイルアップロードWeb API設計の勘所 | フューチャー技術ブログ"
  },
  {
   "path": "/articles/20200828/",
   "pv": "112",
   "title": "チームで推奨するVSCode拡張機能を共有するtips | フューチャー技術ブログ"
  },
  {
   "path": "/articles/20211201a/",
   "pv": "109",
   "title": "巡回セールスマン問題(TSP)の基本的な解き方(ILS) | フューチャー技術ブログ"
  },
  {
   "path": "/articles/20220628a/",
   "pv": "107",
   "title": "資料作成のポイント（定例、課題解決用） | フューチャー技術ブログ"
  },
  {
   "path": "/articles/20210120/",
   "pv": "105",
   "title": "Androidのビルドバリアントをイチから理解する | フューチャー技術ブログ"
  },
  {
   "path": "/articles/20210823b/",
   "pv": "105",
   "title": "Wiresharkで通信プロトコルを見る | フューチャー技術ブログ"
  },
  {
   "path": "/articles/20200810/",
   "pv": "104",
   "title": "自動売買ツールを自作してみよう | フューチャー技術ブログ"
  },
  {
   "path": "/articles/20220621a/",
   "pv": "103",
   "title": "ファイルダウンロード完全マスター | フューチャー技術ブログ"
  },
  {
   "path": "/articles/20210204/",
   "pv": "101",
   "title": "JP1ジョブ設計のポイント（初級） | フューチャー技術ブログ"
  },
  {
   "path": "/articles/20210331/",
   "pv": "99",
   "title": "今さらながらfindパイセンについてまとめてみた | フューチャー技術ブログ"
  },
  {
   "path": "/articles/20221118a/",
   "pv": "98",
   "title": "MSAL.jsを使ってウェブフロントエンドだけでAzureAD認証する | フューチャー技術ブログ"
  },
  {
   "path": "/articles/20211006b/",
   "pv": "92",
   "title": "AWSクラウドの耐障害性、可用性を高めるための前提知識 | フューチャー技術ブログ"
  },
  {
   "path": "/articles/20200409/",
   "pv": "84",
   "title": "スキーマファースト開発のためのOpenAPI（Swagger）設計規約 | フューチャー技術ブログ"
  },
  {
   "path": "/articles/20231124a/",
   "pv": "83",
   "title": "学習のSHA 〜ハッシュ関数の基本と安全性について学ぶ〜 | フューチャー技術ブログ"
  },
  {
   "path": "/articles/20240830a/",
   "pv": "83",
   "title": "PostgreSQL拡張機能のPLV8を使ってみた | フューチャー技術ブログ"
  },
  {
   "path": "/articles/20240819a/",
   "pv": "79",
   "title": "夏の自由研究連載2024をはじめます | フューチャー技術ブログ"
  },
  {
   "path": "/articles/20210329/",
   "pv": "78",
   "title": "ShellCheckでシェルスクリプトの品質を高めよう | フューチャー技術ブログ"
  },
  {
   "path": "/articles/20191107/",
   "pv": "77",
   "title": "インフラ入門vol.3(ネットワーク冗長化構成) | フューチャー技術ブログ"
  },
  {
   "path": "/articles/20240402a/",
   "pv": "77",
   "title": "Difyで生成AIアプリケーション入門　前編：生成AIアプリケーションをノーコードで開発 | フューチャー技術ブログ"
  },
  {
   "path": "/articles/20240517a/",
   "pv": "75",
   "title": "OpenAPI 3.0.3 と 3.1.0 どっち使う？ | フューチャー技術ブログ"
  },
  {
   "path": "/articles/20240328b/",
   "pv": "74",
   "title": "Terraformでのループ処理と条件分岐 | フューチャー技術ブログ"
  }
 ],
 "yearly": [
  {
   "path": "/articles/20240726a/",
   "pv": "44414",
   "title": "2024年版のDockerfileの考え方＆書き方 | フューチャー技術ブログ"
  },
  {
   "path": "/",
   "pv": "35555",
   "title": "フューチャー技術ブログ"
  },
  {
   "path": "/articles/20240215a/",
   "pv": "28179",
   "title": "龍が如く7のすごいテストをなぜ我々は採用できないのか | フューチャー技術ブログ"
  },
  {
   "path": "/",
   "pv": "27181",
   "title": "(not set)"
  },
  {
   "path": "/articles/20200821/",
   "pv": "27027",
   "title": "エンジニアが最低限理解しておくべきOSSライセンスの基礎知識 | フューチャー技術ブログ"
  },
  {
   "path": "/articles/20231101a/",
   "pv": "21942",
   "title": "設計ドキュメント腐る問題、Git管理で運用してみた結果 | フューチャー技術ブログ"
  },
  {
   "path": "/articles/20211026a/",
   "pv": "21530",
   "title": "AWS利用時に read: connection reset by peer が出たときのリトライ検討 | フューチャー技術ブログ"
  },
  {
   "path": "/articles/20210621a/",
   "pv": "20365",
   "title": "どうしてHTML5が廃止されたのか | フューチャー技術ブログ"
  },
  {
   "path": "/articles/20201223/",
   "pv": "19939",
   "title": "2021年版Pythonの型ヒントの書き方 (for Python 3.9) | フューチャー技術ブログ"
  },
  {
   "path": "/articles/20240410a/",
   "pv": "16399",
   "title": "2024年Gitワークフロー再考 | フューチャー技術ブログ"
  },
  {
   "path": "/articles/20220922a/",
   "pv": "12526",
   "title": "AGPLを理解する: もっとも誤解されたライセンス | フューチャー技術ブログ"
  },
  {
   "path": "/articles/20200116/",
   "pv": "12082",
   "title": "実践Drawio | フューチャー技術ブログ"
  },
  {
   "path": "/articles/20240620a/",
   "pv": "12006",
   "title": "個人的docker composeおすすめtips 9選 | フューチャー技術ブログ"
  },
  {
   "path": "/articles/20231030b/",
   "pv": "10800",
   "title": "腰痛と闘うプログラマー | フューチャー技術ブログ"
  },
  {
   "path": "/articles/20211201a/",
   "pv": "10319",
   "title": "巡回セールスマン問題(TSP)の基本的な解き方(ILS) | フューチャー技術ブログ"
  },
  {
   "path": "/articles/20240611a/",
   "pv": "9434",
   "title": "Gitのブランチの役割を考える | フューチャー技術ブログ"
  },
  {
   "path": "/articles/20200428/",
   "pv": "9212",
   "title": "Vue.jsのslotの機能を初心者にわかるように解説してみた | フューチャー技術ブログ"
  },
  {
   "path": "/articles/20210518a/",
   "pv": "9140",
   "title": "HTTP検索条件、GETにするか？POSTにするか？ | フューチャー技術ブログ"
  },
  {
   "path": "/articles/20211028b/",
   "pv": "8779",
   "title": "OpenAPIにおけるundefinedとnullの設計 | フューチャー技術ブログ"
  },
  {
   "path": "/articles/20230216a/",
   "pv": "8509",
   "title": "Mac 慣れした私に Windows が支給されたので、まず設定したこと | フューチャー技術ブログ"
  },
  {
   "path": "/articles/20221116a/",
   "pv": "8293",
   "title": "Plotly.pyによるデータ可視化のすすめ | フューチャー技術ブログ"
  },
  {
   "path": "/articles/20231116a/",
   "pv": "7559",
   "title": "Python Distilledは幅広い人にPythonの基礎を叩き込む本 | フューチャー技術ブログ"
  },
  {
   "path": "/articles/20200828/",
   "pv": "7201",
   "title": "チームで推奨するVSCode拡張機能を共有するtips | フューチャー技術ブログ"
  },
  {
   "path": "/articles/20200601/",
   "pv": "7151",
   "title": "Goのテストに入門してみよう！ | フューチャー技術ブログ"
  },
  {
   "path": "/articles/20221031b/",
   "pv": "7036",
   "title": "バーチャルデスクトップ環境の現状と、VRの個人的な感想 | フューチャー技術ブログ"
  },
  {
   "path": "/articles/20240705a/",
   "pv": "6975",
   "title": "署名付きURLを利用したファイルアップロードWeb API設計の勘所 | フューチャー技術ブログ"
  },
  {
   "path": "/articles/20200409/",
   "pv": "6745",
   "title": "スキーマファースト開発のためのOpenAPI（Swagger）設計規約 | フューチャー技術ブログ"
  },
  {
   "path": "/articles/20231012a/",
   "pv": "6408",
   "title": "Makefile覚書: Goアプリ開発に役立ちそうな基礎知識 | フューチャー技術ブログ"
  },
  {
   "path": "/articles/20210120/",
   "pv": "6299",
   "title": "Androidのビルドバリアントをイチから理解する | フューチャー技術ブログ"
  },
  {
   "path": "/articles/20191008/",
   "pv": "6292",
   "title": "本当に使ってよかったOpenAPI (Swagger) ツール | フューチャー技術ブログ"
  },
  {
   "path": "/articles/20210823b/",
   "pv": "6208",
   "title": "Wiresharkで通信プロトコルを見る | フューチャー技術ブログ"
  },
  {
   "path": "/articles/20220530a/",
   "pv": "6205",
   "title": "【エネルギー業界】LPガス基礎part2 供給設備編 | フューチャー技術ブログ"
  },
  {
   "path": "/articles/20220621a/",
   "pv": "6185",
   "title": "ファイルダウンロード完全マスター | フューチャー技術ブログ"
  },
  {
   "path": "/articles/20210401/",
   "pv": "5729",
   "title": "declare使ってBashで配列と連想配列 | フューチャー技術ブログ"
  },
  {
   "path": "/articles/20230822a/",
   "pv": "5687",
   "title": "Playwrightのインストール方法と使い方 | フューチャー技術ブログ"
  },
  {
   "path": "/articles/20200818/",
   "pv": "5550",
   "title": "【入門】私を苦しめたDynamoDB | フューチャー技術ブログ"
  },
  {
   "path": "/articles/20191107/",
   "pv": "5456",
   "title": "インフラ入門vol.3(ネットワーク冗長化構成) | フューチャー技術ブログ"
  },
  {
   "path": "/articles/20210204/",
   "pv": "5300",
   "title": "JP1ジョブ設計のポイント（初級） | フューチャー技術ブログ"
  },
  {
   "path": "/articles/20200810/",
   "pv": "5243",
   "title": "自動売買ツールを自作してみよう | フューチャー技術ブログ"
  },
  {
   "path": "/articles/20210331/",
   "pv": "5229",
   "title": "今さらながらfindパイセンについてまとめてみた | フューチャー技術ブログ"
  },
  {
   "path": "/articles/20230313a/",
   "pv": "5112",
   "title": "【エネルギー業界】国家資格「高圧ガス第二種販売主任者」合格までの道のり | フューチャー技術ブログ"
  },
  {
   "path": "/articles/20200513/",
   "pv": "5109",
   "title": "仕事でPythonコンテナをデプロイする人向けのDockerfile (1): オールマイティ編 | フューチャー技術ブログ"
  },
  {
   "path": "/articles/20220222a/",
   "pv": "4952",
   "title": "CORSエラーのトラブルシューティング入門 | フューチャー技術ブログ"
  },
  {
   "path": "/articles/20221012a/",
   "pv": "4925",
   "title": "OAuth の仕組みを理解しながらクライアントを実装してみる | フューチャー技術ブログ"
  },
  {
   "path": "/articles/20211220a/",
   "pv": "4869",
   "title": "JavaのDockerイメージ何選ぶ？ | フューチャー技術ブログ"
  },
  {
   "path": "/articles/20220929a/",
   "pv": "4814",
   "title": "AGPLが適する場所、適さない場所 | フューチャー技術ブログ"
  },
  {
   "path": "/articles/20220628a/",
   "pv": "4756",
   "title": "資料作成のポイント（定例、課題解決用） | フューチャー技術ブログ"
  },
  {
   "path": "/articles/20231128a/",
   "pv": "4744",
   "title": "data-testidはいつ使うべきか？そもそも使うべきなのか？ | フューチャー技術ブログ"
  },
  {
   "path": "/articles/20240628a/",
   "pv": "4669",
   "title": "PostgreSQLのPub/Sub機能とJavaのクライアント実装 | フューチャー技術ブログ"
  },
  {
   "path": "/articles/20201117/",
   "pv": "4590",
   "title": "Goのデバッグ環境 on VSCode | フューチャー技術ブログ"
  }
 ]
}
