{
 "monthly": [
  {
   "path": "/articles/20251212a/",
   "pv": "9086",
   "title": "AWS設計ガイドラインを公開しました | フューチャー技術ブログ"
  },
  {
   "path": "/articles/20251211a/",
   "pv": "2196",
   "title": "システム開発からデータ分析へ。やってみて気づいた技術選定と実装のポイント | フューチャー技術ブログ"
  },
  {
   "path": "/",
   "pv": "1745",
   "title": "フューチャー技術ブログ"
  },
  {
   "path": "/articles/20251218a/",
   "pv": "1046",
   "title": "Software Design 2026年1月号のアルゴリズム特集に寄稿したお話 | フューチャー技術ブログ"
  },
  {
   "path": "/articles/20240415a/",
   "pv": "960",
   "title": "VSCodeでGitLensを使う | フューチャー技術ブログ"
  },
  {
   "path": "/articles/20240726a/",
   "pv": "954",
   "title": "2024年版のDockerfileの考え方＆書き方 | フューチャー技術ブログ"
  },
  {
   "path": "/articles/20241113a/",
   "pv": "867",
   "title": "PostgreSQLで連番を自動生成するIDENTITY列。SERIALとどちらを使うべきか | フューチャー技術ブログ"
  },
  {
   "path": "/articles/20230216a/",
   "pv": "539",
   "title": "Mac 慣れした私に Windows が支給されたので、まず設定したこと | フューチャー技術ブログ"
  },
  {
   "path": "/articles/20200821/",
   "pv": "536",
   "title": "エンジニアが最低限理解しておくべきOSSライセンスの基礎知識 | フューチャー技術ブログ"
  },
  {
   "path": "/articles/20231101a/",
   "pv": "420",
   "title": "設計ドキュメント腐る問題、Git管理で運用してみた結果 | フューチャー技術ブログ"
  },
  {
   "path": "/articles/20250509a/",
   "pv": "399",
   "title": "Goのテストをはじめてみよう（2025年版） | フューチャー技術ブログ"
  },
  {
   "path": "/articles/20200116/",
   "pv": "358",
   "title": "実践Drawio | フューチャー技術ブログ"
  },
  {
   "path": "/articles/20250417a/",
   "pv": "357",
   "title": "GitLabのレビューにPR-Agentを組み込んでみた | フューチャー技術ブログ"
  },
  {
   "path": "/articles/20250905a/",
   "pv": "329",
   "title": "Mermaid図の調整ツールで図をさらに見やすく！〜現場の課題を解決する自作ツール〜 | フューチャー技術ブログ"
  },
  {
   "path": "/articles/20211201a/",
   "pv": "320",
   "title": "巡回セールスマン問題(TSP)の基本的な解き方(ILS) | フューチャー技術ブログ"
  },
  {
   "path": "/articles/20220922a/",
   "pv": "296",
   "title": "AGPLを理解する: もっとも誤解されたライセンス | フューチャー技術ブログ"
  },
  {
   "path": "/articles/20251229a/",
   "pv": "272",
   "title": "データマネジメント設計ガイドラインを公開しました | フューチャー技術ブログ"
  },
  {
   "path": "/articles/20231128a/",
   "pv": "262",
   "title": "data-testidはいつ使うべきか？そもそも使うべきなのか？ | フューチャー技術ブログ"
  },
  {
   "path": "/articles/20240626b/",
   "pv": "261",
   "title": "社会人からはじめる競技プログラミング | フューチャー技術ブログ"
  },
  {
   "path": "/articles/20250602a/",
   "pv": "259",
   "title": "FastAPI on Dockerがかなりシンプルになった(2025年版) | フューチャー技術ブログ"
  },
  {
   "path": "/articles/20220530a/",
   "pv": "249",
   "title": "【エネルギー業界】LPガス基礎part2 供給設備編 | フューチャー技術ブログ"
  },
  {
   "path": "/articles/20251117a/",
   "pv": "247",
   "title": "AI暴走を防ごう！AIエージェントのガードレールの作り方を考えてみよう | フューチャー技術ブログ"
  },
  {
   "path": "/articles/20250325a/",
   "pv": "233",
   "title": "【実践編】HTTPS通信の中身を見て、どのようにしてセキュアな通信が確立されるかを理解する | フューチャー技術ブログ"
  },
  {
   "path": "/articles/20251208a/",
   "pv": "233",
   "title": "プログラミング未経験の学生が選択すると良さそうな生成AIツールと考え方 | フューチャー技術ブログ"
  },
  {
   "path": "/articles/20240419a/",
   "pv": "232",
   "title": "CI/CD初心者のためのJenkins入門 | フューチャー技術ブログ"
  },
  {
   "path": "/articles/20251110a/",
   "pv": "229",
   "title": "情報処理安全確保支援士試験に合格しました | フューチャー技術ブログ"
  },
  {
   "path": "/articles/20251107a/",
   "pv": "226",
   "title": "なぜアーキチームは設計や実装のパターンを絞りたいか？ 背景にある思考と技術選定のジレンマ | フューチャー技術ブログ"
  },
  {
   "path": "/articles/20250516a/",
   "pv": "225",
   "title": "Terraformの基本のキ！ファイル構成からコマンドまでやさしく解説 | フューチャー技術ブログ"
  },
  {
   "path": "/articles/20230310a/",
   "pv": "211",
   "title": "本当は怖い、逆コンウェイ戦略 | フューチャー技術ブログ"
  },
  {
   "path": "/articles/20210204/",
   "pv": "210",
   "title": "JP1ジョブ設計のポイント（初級） | フューチャー技術ブログ"
  },
  {
   "path": "/articles/20240620a/",
   "pv": "209",
   "title": "個人的docker composeおすすめtips 9選 | フューチャー技術ブログ"
  },
  {
   "path": "/articles/20250911a/",
   "pv": "209",
   "title": "Webフロントエンド設計ガイドラインを公開しました | フューチャー技術ブログ"
  },
  {
   "path": "/articles/20240705a/",
   "pv": "207",
   "title": "署名付きURLを利用したファイルアップロードWeb API設計の勘所 | フューチャー技術ブログ"
  },
  {
   "path": "/articles/20250425a/",
   "pv": "207",
   "title": "VS CodeによるiOSアプリ開発入門〜ビルド＆ラン〜 | フューチャー技術ブログ"
  },
  {
   "path": "/articles/20200810/",
   "pv": "206",
   "title": "自動売買ツールを自作してみよう | フューチャー技術ブログ"
  },
  {
   "path": "/articles/20220628a/",
   "pv": "196",
   "title": "資料作成のポイント（定例、課題解決用） | フューチャー技術ブログ"
  },
  {
   "path": "/articles/20250829a/",
   "pv": "192",
   "title": "PostgreSQLの全文検索機能を試してみる | フューチャー技術ブログ"
  },
  {
   "path": "/articles/20231124a/",
   "pv": "185",
   "title": "学習のSHA 〜ハッシュ関数の基本と安全性について学ぶ〜 | フューチャー技術ブログ"
  },
  {
   "path": "/articles/20240611a/",
   "pv": "185",
   "title": "Gitのブランチの役割を考える | フューチャー技術ブログ"
  },
  {
   "path": "/articles/20200828/",
   "pv": "178",
   "title": "チームで推奨するVSCode拡張機能を共有するtips | フューチャー技術ブログ"
  },
  {
   "path": "/articles/20210331/",
   "pv": "174",
   "title": "今さらながらfindパイセンについてまとめてみた | フューチャー技術ブログ"
  },
  {
   "path": "/articles/20240603a/",
   "pv": "171",
   "title": "Cloudflare R2 + NextCloudで作る自分専用クラウドストレージのススメ | フューチャー技術ブログ"
  },
  {
   "path": "/articles/20250530a/",
   "pv": "171",
   "title": "PostgreSQL設計ガイドラインのご紹介 | フューチャー技術ブログ"
  },
  {
   "path": "/articles/20221012a/",
   "pv": "169",
   "title": "OAuth の仕組みを理解しながらクライアントを実装してみる | フューチャー技術ブログ"
  },
  {
   "path": "/articles/20231206a/",
   "pv": "169",
   "title": "Dev Containersの始め方(1) : 仕組み編 | フューチャー技術ブログ"
  },
  {
   "path": "/articles/",
   "pv": "167",
   "title": "Archives | フューチャー技術ブログ"
  },
  {
   "path": "/articles/20241030a/",
   "pv": "167",
   "title": "TryHackMe でセキュリティを気軽に学ぶ | フューチャー技術ブログ"
  },
  {
   "path": "/articles/20191107/",
   "pv": "166",
   "title": "インフラ入門vol.3(ネットワーク冗長化構成) | フューチャー技術ブログ"
  },
  {
   "path": "/articles/20250620a/",
   "pv": "165",
   "title": "Gemma3 + Unsloth + GitLab CI/CDで構築する完全オンプレミスAIコードレビュー環境 | フューチャー技術ブログ"
  },
  {
   "path": "/articles/20240517a/",
   "pv": "162",
   "title": "OpenAPI 3.0.3 と 3.1.0 どっち使う？ | フューチャー技術ブログ"
  }
 ],
 "weekly": [
  {
   "path": "/",
   "pv": "443",
   "title": "フューチャー技術ブログ"
  },
  {
   "path": "/articles/20240415a/",
   "pv": "296",
   "title": "VSCodeでGitLensを使う | フューチャー技術ブログ"
  },
  {
   "path": "/articles/20241113a/",
   "pv": "255",
   "title": "PostgreSQLで連番を自動生成するIDENTITY列。SERIALとどちらを使うべきか | フューチャー技術ブログ"
  },
  {
   "path": "/articles/20240726a/",
   "pv": "222",
   "title": "2024年版のDockerfileの考え方＆書き方 | フューチャー技術ブログ"
  },
  {
   "path": "/articles/20251212a/",
   "pv": "188",
   "title": "AWS設計ガイドラインを公開しました | フューチャー技術ブログ"
  },
  {
   "path": "/articles/20230216a/",
   "pv": "151",
   "title": "Mac 慣れした私に Windows が支給されたので、まず設定したこと | フューチャー技術ブログ"
  },
  {
   "path": "/articles/20251229a/",
   "pv": "127",
   "title": "データマネジメント設計ガイドラインを公開しました | フューチャー技術ブログ"
  },
  {
   "path": "/articles/20200116/",
   "pv": "126",
   "title": "実践Drawio | フューチャー技術ブログ"
  },
  {
   "path": "/articles/20250509a/",
   "pv": "125",
   "title": "Goのテストをはじめてみよう（2025年版） | フューチャー技術ブログ"
  },
  {
   "path": "/articles/20200821/",
   "pv": "124",
   "title": "エンジニアが最低限理解しておくべきOSSライセンスの基礎知識 | フューチャー技術ブログ"
  },
  {
   "path": "/articles/20250417a/",
   "pv": "120",
   "title": "GitLabのレビューにPR-Agentを組み込んでみた | フューチャー技術ブログ"
  },
  {
   "path": "/articles/20231101a/",
   "pv": "117",
   "title": "設計ドキュメント腐る問題、Git管理で運用してみた結果 | フューチャー技術ブログ"
  },
  {
   "path": "/articles/20250905a/",
   "pv": "105",
   "title": "Mermaid図の調整ツールで図をさらに見やすく！〜現場の課題を解決する自作ツール〜 | フューチャー技術ブログ"
  },
  {
   "path": "/articles/20220922a/",
   "pv": "85",
   "title": "AGPLを理解する: もっとも誤解されたライセンス | フューチャー技術ブログ"
  },
  {
   "path": "/articles/20211201a/",
   "pv": "83",
   "title": "巡回セールスマン問題(TSP)の基本的な解き方(ILS) | フューチャー技術ブログ"
  },
  {
   "path": "/articles/20240419a/",
   "pv": "76",
   "title": "CI/CD初心者のためのJenkins入門 | フューチャー技術ブログ"
  },
  {
   "path": "/articles/20200810/",
   "pv": "74",
   "title": "自動売買ツールを自作してみよう | フューチャー技術ブログ"
  },
  {
   "path": "/articles/20220530a/",
   "pv": "74",
   "title": "【エネルギー業界】LPガス基礎part2 供給設備編 | フューチャー技術ブログ"
  },
  {
   "path": "/articles/20231128a/",
   "pv": "72",
   "title": "data-testidはいつ使うべきか？そもそも使うべきなのか？ | フューチャー技術ブログ"
  },
  {
   "path": "/articles/20250325a/",
   "pv": "72",
   "title": "【実践編】HTTPS通信の中身を見て、どのようにしてセキュアな通信が確立されるかを理解する | フューチャー技術ブログ"
  },
  {
   "path": "/articles/20251117a/",
   "pv": "69",
   "title": "AI暴走を防ごう！AIエージェントのガードレールの作り方を考えてみよう | フューチャー技術ブログ"
  },
  {
   "path": "/articles/20220222a/",
   "pv": "67",
   "title": "CORSエラーのトラブルシューティング入門 | フューチャー技術ブログ"
  },
  {
   "path": "/articles/20250516a/",
   "pv": "66",
   "title": "Terraformの基本のキ！ファイル構成からコマンドまでやさしく解説 | フューチャー技術ブログ"
  },
  {
   "path": "/articles/20250602a/",
   "pv": "66",
   "title": "FastAPI on Dockerがかなりシンプルになった(2025年版) | フューチャー技術ブログ"
  },
  {
   "path": "/articles/20200828/",
   "pv": "65",
   "title": "チームで推奨するVSCode拡張機能を共有するtips | フューチャー技術ブログ"
  },
  {
   "path": "/articles/20230310a/",
   "pv": "61",
   "title": "本当は怖い、逆コンウェイ戦略 | フューチャー技術ブログ"
  },
  {
   "path": "/articles/20240705a/",
   "pv": "59",
   "title": "署名付きURLを利用したファイルアップロードWeb API設計の勘所 | フューチャー技術ブログ"
  },
  {
   "path": "/articles/20250619a/",
   "pv": "59",
   "title": "GitHub ActionsのCI/CDパイプラインに静的コード解析Sonar Qubeを組み込んでみた | フューチャー技術ブログ"
  },
  {
   "path": "/articles/20221012a/",
   "pv": "55",
   "title": "OAuth の仕組みを理解しながらクライアントを実装してみる | フューチャー技術ブログ"
  },
  {
   "path": "/articles/20231206a/",
   "pv": "55",
   "title": "Dev Containersの始め方(1) : 仕組み編 | フューチャー技術ブログ"
  },
  {
   "path": "/articles/20240620a/",
   "pv": "54",
   "title": "個人的docker composeおすすめtips 9選 | フューチャー技術ブログ"
  },
  {
   "path": "/articles/20240626b/",
   "pv": "54",
   "title": "社会人からはじめる競技プログラミング | フューチャー技術ブログ"
  },
  {
   "path": "/articles/20251110a/",
   "pv": "54",
   "title": "情報処理安全確保支援士試験に合格しました | フューチャー技術ブログ"
  },
  {
   "path": "/articles/20231124a/",
   "pv": "53",
   "title": "学習のSHA 〜ハッシュ関数の基本と安全性について学ぶ〜 | フューチャー技術ブログ"
  },
  {
   "path": "/articles/20250829a/",
   "pv": "53",
   "title": "PostgreSQLの全文検索機能を試してみる | フューチャー技術ブログ"
  },
  {
   "path": "/articles/20221025a/",
   "pv": "52",
   "title": "A5:SQL Mk-2 （a5m2）のデータモデリング便利機能（初心者向け） | フューチャー技術ブログ"
  },
  {
   "path": "/articles/20240227a/",
   "pv": "52",
   "title": "ローカルプロキシで認証プロキシの煩わしさを解消！ | フューチャー技術ブログ"
  },
  {
   "path": "/articles/20220628a/",
   "pv": "50",
   "title": "資料作成のポイント（定例、課題解決用） | フューチャー技術ブログ"
  },
  {
   "path": "/articles/20210204/",
   "pv": "49",
   "title": "JP1ジョブ設計のポイント（初級） | フューチャー技術ブログ"
  },
  {
   "path": "/articles/20210401/",
   "pv": "49",
   "title": "declare使ってBashで配列と連想配列 | フューチャー技術ブログ"
  },
  {
   "path": "/articles/20210705a/",
   "pv": "48",
   "title": "キューとリングバッファについてやさしい言葉で解説してみる | フューチャー技術ブログ"
  },
  {
   "path": "/articles/20200428/",
   "pv": "47",
   "title": "Vue.jsのslotの機能を初心者にわかるように解説してみた | フューチャー技術ブログ"
  },
  {
   "path": "/articles/20240611a/",
   "pv": "47",
   "title": "Gitのブランチの役割を考える | フューチャー技術ブログ"
  },
  {
   "path": "/articles/20250425a/",
   "pv": "47",
   "title": "VS CodeによるiOSアプリ開発入門〜ビルド＆ラン〜 | フューチャー技術ブログ"
  },
  {
   "path": "/articles/20250911a/",
   "pv": "47",
   "title": "Webフロントエンド設計ガイドラインを公開しました | フューチャー技術ブログ"
  },
  {
   "path": "/articles/",
   "pv": "45",
   "title": "Archives | フューチャー技術ブログ"
  },
  {
   "path": "/articles/20210518a/",
   "pv": "44",
   "title": "HTTP検索条件、GETにするか？POSTにするか？ | フューチャー技術ブログ"
  },
  {
   "path": "/articles/20201223/",
   "pv": "43",
   "title": "2021年版Pythonの型ヒントの書き方 (for Python 3.9) | フューチャー技術ブログ"
  },
  {
   "path": "/articles/20240517a/",
   "pv": "43",
   "title": "OpenAPI 3.0.3 と 3.1.0 どっち使う？ | フューチャー技術ブログ"
  },
  {
   "path": "/articles/20250620a/",
   "pv": "43",
   "title": "Gemma3 + Unsloth + GitLab CI/CDで構築する完全オンプレミスAIコードレビュー環境 | フューチャー技術ブログ"
  }
 ],
 "yearly": [
  {
   "path": "/",
   "pv": "30996",
   "title": "フューチャー技術ブログ"
  },
  {
   "path": "/articles/20240726a/",
   "pv": "15379",
   "title": "2024年版のDockerfileの考え方＆書き方 | フューチャー技術ブログ"
  },
  {
   "path": "/articles/20250324a/",
   "pv": "14789",
   "title": "【理論編】HTTPS通信の中身を見て、どのようにしてセキュアな通信が確立されるかを理解する | フューチャー技術ブログ"
  },
  {
   "path": "/articles/20241113a/",
   "pv": "14500",
   "title": "PostgreSQLで連番を自動生成するIDENTITY列。SERIALとどちらを使うべきか | フューチャー技術ブログ"
  },
  {
   "path": "/articles/20200821/",
   "pv": "13473",
   "title": "エンジニアが最低限理解しておくべきOSSライセンスの基礎知識 | フューチャー技術ブログ"
  },
  {
   "path": "/articles/20240415a/",
   "pv": "12846",
   "title": "VSCodeでGitLensを使う | フューチャー技術ブログ"
  },
  {
   "path": "/articles/20250602a/",
   "pv": "11300",
   "title": "FastAPI on Dockerがかなりシンプルになった(2025年版) | フューチャー技術ブログ"
  },
  {
   "path": "/articles/20250911a/",
   "pv": "10364",
   "title": "Webフロントエンド設計ガイドラインを公開しました | フューチャー技術ブログ"
  },
  {
   "path": "/articles/20251106a/",
   "pv": "10346",
   "title": "データベースと向き合う決意をしてから3年たった | フューチャー技術ブログ"
  },
  {
   "path": "/articles/20251212a/",
   "pv": "9082",
   "title": "AWS設計ガイドラインを公開しました | フューチャー技術ブログ"
  },
  {
   "path": "/articles/20251107a/",
   "pv": "9035",
   "title": "なぜアーキチームは設計や実装のパターンを絞りたいか？ 背景にある思考と技術選定のジレンマ | フューチャー技術ブログ"
  },
  {
   "path": "/articles/20250530a/",
   "pv": "8753",
   "title": "PostgreSQL設計ガイドラインのご紹介 | フューチャー技術ブログ"
  },
  {
   "path": "/articles/20230216a/",
   "pv": "8092",
   "title": "Mac 慣れした私に Windows が支給されたので、まず設定したこと | フューチャー技術ブログ"
  },
  {
   "path": "/articles/20231101a/",
   "pv": "7748",
   "title": "設計ドキュメント腐る問題、Git管理で運用してみた結果 | フューチャー技術ブログ"
  },
  {
   "path": "/articles/20250918a/",
   "pv": "6984",
   "title": "バッチ設計ガイドラインを公開しました | フューチャー技術ブログ"
  },
  {
   "path": "/articles/20250513b/",
   "pv": "6913",
   "title": "Web API設計ガイドラインを公開しました | フューチャー技術ブログ"
  },
  {
   "path": "/articles/20250829a/",
   "pv": "6797",
   "title": "PostgreSQLの全文検索機能を試してみる | フューチャー技術ブログ"
  },
  {
   "path": "/articles/20250728a/",
   "pv": "6788",
   "title": "GoogleカレンダーをGeminiアプリの外部記憶装置として活用する | フューチャー技術ブログ"
  },
  {
   "path": "/articles/20200116/",
   "pv": "6421",
   "title": "実践Drawio | フューチャー技術ブログ"
  },
  {
   "path": "/articles/20250409a/",
   "pv": "6410",
   "title": "Terraform設計ガイドラインを公開しました | フューチャー技術ブログ"
  },
  {
   "path": "/articles/20220922a/",
   "pv": "6344",
   "title": "AGPLを理解する: もっとも誤解されたライセンス | フューチャー技術ブログ"
  },
  {
   "path": "/articles/20251014a/",
   "pv": "5709",
   "title": "PostgreSQL 18の新機能「B-treeインデックスのスキップスキャン」 | フューチャー技術ブログ"
  },
  {
   "path": "/articles/20240419a/",
   "pv": "5543",
   "title": "CI/CD初心者のためのJenkins入門 | フューチャー技術ブログ"
  },
  {
   "path": "/articles/20250509a/",
   "pv": "5497",
   "title": "Goのテストをはじめてみよう（2025年版） | フューチャー技術ブログ"
  },
  {
   "path": "/articles/20250428a/",
   "pv": "5425",
   "title": "CursorによるAI駆動開発入門 | フューチャー技術ブログ"
  },
  {
   "path": "/articles/20211201a/",
   "pv": "5354",
   "title": "巡回セールスマン問題(TSP)の基本的な解き方(ILS) | フューチャー技術ブログ"
  },
  {
   "path": "/articles/20220530a/",
   "pv": "5023",
   "title": "【エネルギー業界】LPガス基礎part2 供給設備編 | フューチャー技術ブログ"
  },
  {
   "path": "/articles/20211026a/",
   "pv": "4927",
   "title": "AWS利用時に read: connection reset by peer が出たときのリトライ検討 | フューチャー技術ブログ"
  },
  {
   "path": "/articles/20210621a/",
   "pv": "4761",
   "title": "どうしてHTML5が廃止されたのか | フューチャー技術ブログ"
  },
  {
   "path": "/articles/20251003a/",
   "pv": "4581",
   "title": "メール設計ガイドラインを公開しました | フューチャー技術ブログ"
  },
  {
   "path": "/articles/20250818a/",
   "pv": "4455",
   "title": "I/F設計ガイドラインを公開しました | フューチャー技術ブログ"
  },
  {
   "path": "/articles/20250610a/",
   "pv": "4292",
   "title": "macOS 26でLinuxコンテナのネイティブサポートが来る | フューチャー技術ブログ"
  },
  {
   "path": "/articles/20200828/",
   "pv": "4282",
   "title": "チームで推奨するVSCode拡張機能を共有するtips | フューチャー技術ブログ"
  },
  {
   "path": "/articles/20220628a/",
   "pv": "4132",
   "title": "資料作成のポイント（定例、課題解決用） | フューチャー技術ブログ"
  },
  {
   "path": "/articles/20240705a/",
   "pv": "4111",
   "title": "署名付きURLを利用したファイルアップロードWeb API設計の勘所 | フューチャー技術ブログ"
  },
  {
   "path": "/articles/20250827a/",
   "pv": "4077",
   "title": "リスクアセスメント　ーリスクの可視化から意思決定までー | フューチャー技術ブログ"
  },
  {
   "path": "/articles/20231128a/",
   "pv": "4036",
   "title": "data-testidはいつ使うべきか？そもそも使うべきなのか？ | フューチャー技術ブログ"
  },
  {
   "path": "/articles/20211028b/",
   "pv": "3889",
   "title": "OpenAPIにおけるundefinedとnullの設計 | フューチャー技術ブログ"
  },
  {
   "path": "/articles/20250604a/",
   "pv": "3822",
   "title": "GitHub 標準の Annotation を活用してレビューを可視化する | フューチャー技術ブログ"
  },
  {
   "path": "/articles/20200810/",
   "pv": "3680",
   "title": "自動売買ツールを自作してみよう | フューチャー技術ブログ"
  },
  {
   "path": "/articles/20210518a/",
   "pv": "3575",
   "title": "HTTP検索条件、GETにするか？POSTにするか？ | フューチャー技術ブログ"
  },
  {
   "path": "/articles/20250620a/",
   "pv": "3549",
   "title": "Gemma3 + Unsloth + GitLab CI/CDで構築する完全オンプレミスAIコードレビュー環境 | フューチャー技術ブログ"
  },
  {
   "path": "/articles/20250729a/",
   "pv": "3545",
   "title": "伸びる人の条件についてSlackで話した | フューチャー技術ブログ"
  },
  {
   "path": "/articles/20250708a/",
   "pv": "3470",
   "title": "プロンプトエンジニアリングから逆算して考える、エンジニアのスキルアップ | フューチャー技術ブログ"
  },
  {
   "path": "/articles/20210823b/",
   "pv": "3466",
   "title": "Wiresharkで通信プロトコルを見る | フューチャー技術ブログ"
  },
  {
   "path": "/articles/20210204/",
   "pv": "3439",
   "title": "JP1ジョブ設計のポイント（初級） | フューチャー技術ブログ"
  },
  {
   "path": "/articles/20250417a/",
   "pv": "3368",
   "title": "GitLabのレビューにPR-Agentを組み込んでみた | フューチャー技術ブログ"
  },
  {
   "path": "/articles/20201223/",
   "pv": "3349",
   "title": "2021年版Pythonの型ヒントの書き方 (for Python 3.9) | フューチャー技術ブログ"
  },
  {
   "path": "/articles/20250314a/",
   "pv": "3329",
   "title": "Tailwind CSSのドキュメントから見えてくる使い方とCSS設計のヒント | フューチャー技術ブログ"
  },
  {
   "path": "/articles/20250722a/",
   "pv": "3288",
   "title": "生成AIとはじめる、バックオフィス業務改革 ～Geminiの有効な使い方～ | フューチャー技術ブログ"
  }
 ]
}
