{
 "monthly": [
  {
   "path": "/",
   "pv": "7225",
   "title": "(not set)"
  },
  {
   "path": "/",
   "pv": "1746",
   "title": "フューチャー技術ブログ"
  },
  {
   "path": "/articles/20240726a/",
   "pv": "1704",
   "title": "2024年版のDockerfileの考え方＆書き方 | フューチャー技術ブログ"
  },
  {
   "path": "/articles/20241226a/",
   "pv": "1495",
   "title": "Fast APIのすすめ（概要編） | フューチャー技術ブログ"
  },
  {
   "path": "/articles/20200821/",
   "pv": "1180",
   "title": "エンジニアが最低限理解しておくべきOSSライセンスの基礎知識 | フューチャー技術ブログ"
  },
  {
   "path": "/articles/20230216a/",
   "pv": "837",
   "title": "Mac 慣れした私に Windows が支給されたので、まず設定したこと | フューチャー技術ブログ"
  },
  {
   "path": "/articles/20211026a/",
   "pv": "817",
   "title": "AWS利用時に read: connection reset by peer が出たときのリトライ検討 | フューチャー技術ブログ"
  },
  {
   "path": "/articles/20220922a/",
   "pv": "691",
   "title": "AGPLを理解する: もっとも誤解されたライセンス | フューチャー技術ブログ"
  },
  {
   "path": "/articles/20211201a/",
   "pv": "682",
   "title": "巡回セールスマン問題(TSP)の基本的な解き方(ILS) | フューチャー技術ブログ"
  },
  {
   "path": "/articles/20240415a/",
   "pv": "670",
   "title": "VSCodeでGitLensを使う | フューチャー技術ブログ"
  },
  {
   "path": "/articles/20240419a/",
   "pv": "668",
   "title": "CI/CD初心者のためのJenkins入門 | フューチャー技術ブログ"
  },
  {
   "path": "/articles/20241113a/",
   "pv": "661",
   "title": "PostgreSQLで連番を自動生成するIDENTITY列。SERIALとどちらを使うべきか | フューチャー技術ブログ"
  },
  {
   "path": "/articles/20201223/",
   "pv": "568",
   "title": "2021年版Pythonの型ヒントの書き方 (for Python 3.9) | フューチャー技術ブログ"
  },
  {
   "path": "/articles/20210621a/",
   "pv": "534",
   "title": "どうしてHTML5が廃止されたのか | フューチャー技術ブログ"
  },
  {
   "path": "/articles/20200810/",
   "pv": "515",
   "title": "自動売買ツールを自作してみよう | フューチャー技術ブログ"
  },
  {
   "path": "/articles/20231101a/",
   "pv": "495",
   "title": "設計ドキュメント腐る問題、Git管理で運用してみた結果 | フューチャー技術ブログ"
  },
  {
   "path": "/articles/20200116/",
   "pv": "446",
   "title": "実践Drawio | フューチャー技術ブログ"
  },
  {
   "path": "/articles/20211028b/",
   "pv": "409",
   "title": "OpenAPIにおけるundefinedとnullの設計 | フューチャー技術ブログ"
  },
  {
   "path": "/articles/20220530a/",
   "pv": "397",
   "title": "【エネルギー業界】LPガス基礎part2 供給設備編 | フューチャー技術ブログ"
  },
  {
   "path": "/articles/20210518a/",
   "pv": "380",
   "title": "HTTP検索条件、GETにするか？POSTにするか？ | フューチャー技術ブログ"
  },
  {
   "path": "/articles/20200828/",
   "pv": "377",
   "title": "チームで推奨するVSCode拡張機能を共有するtips | フューチャー技術ブログ"
  },
  {
   "path": "/articles/20241111a/",
   "pv": "373",
   "title": "フロントエンドフレームワークからサーバーにアクセスするパターン | フューチャー技術ブログ"
  },
  {
   "path": "/articles/20240705a/",
   "pv": "345",
   "title": "署名付きURLを利用したファイルアップロードWeb API設計の勘所 | フューチャー技術ブログ"
  },
  {
   "path": "/articles/20240620a/",
   "pv": "330",
   "title": "個人的docker composeおすすめtips 9選 | フューチャー技術ブログ"
  },
  {
   "path": "/articles/20220628a/",
   "pv": "327",
   "title": "資料作成のポイント（定例、課題解決用） | フューチャー技術ブログ"
  },
  {
   "path": "/articles/20200428/",
   "pv": "320",
   "title": "Vue.jsのslotの機能を初心者にわかるように解説してみた | フューチャー技術ブログ"
  },
  {
   "path": "/articles/20241227a/",
   "pv": "308",
   "title": "新卒 2 年目社員の Software Design 寄稿 | フューチャー技術ブログ"
  },
  {
   "path": "/articles/20220621a/",
   "pv": "305",
   "title": "ファイルダウンロード完全マスター | フューチャー技術ブログ"
  },
  {
   "path": "/articles/20210823b/",
   "pv": "301",
   "title": "Wiresharkで通信プロトコルを見る | フューチャー技術ブログ"
  },
  {
   "path": "/articles/20250109a/",
   "pv": "291",
   "title": "構造化テキスト(URL)を文字列結合で作らないようにするライブラリを作ってみた | フューチャー技術ブログ"
  },
  {
   "path": "/articles/20210331/",
   "pv": "283",
   "title": "今さらながらfindパイセンについてまとめてみた | フューチャー技術ブログ"
  },
  {
   "path": "/articles/20210401/",
   "pv": "281",
   "title": "declare使ってBashで配列と連想配列 | フューチャー技術ブログ"
  },
  {
   "path": "/articles/20231128a/",
   "pv": "281",
   "title": "data-testidはいつ使うべきか？そもそも使うべきなのか？ | フューチャー技術ブログ"
  },
  {
   "path": "/articles/20241214a/",
   "pv": "275",
   "title": "Gitブランチフロー規約の紹介 | フューチャー技術ブログ"
  },
  {
   "path": "/articles/20241205a/",
   "pv": "262",
   "title": "TypeScript/JavaScript Array完全攻略2024 | フューチャー技術ブログ"
  },
  {
   "path": "/articles/20200409/",
   "pv": "244",
   "title": "スキーマファースト開発のためのOpenAPI（Swagger）設計規約 | フューチャー技術ブログ"
  },
  {
   "path": "/articles/20191107/",
   "pv": "239",
   "title": "インフラ入門vol.3(ネットワーク冗長化構成) | フューチャー技術ブログ"
  },
  {
   "path": "/articles/20231214a/",
   "pv": "232",
   "title": "React Server ComponentでもContextで状態を共有する | フューチャー技術ブログ"
  },
  {
   "path": "/articles/20200601/",
   "pv": "229",
   "title": "Goのテストに入門してみよう！ | フューチャー技術ブログ"
  },
  {
   "path": "/articles/20220713a/",
   "pv": "229",
   "title": "【エネルギー業界】LPガス基礎part4 バルク配送入門 | フューチャー技術ブログ"
  },
  {
   "path": "/articles/20210204/",
   "pv": "224",
   "title": "JP1ジョブ設計のポイント（初級） | フューチャー技術ブログ"
  },
  {
   "path": "/articles/20220929a/",
   "pv": "223",
   "title": "AGPLが適する場所、適さない場所 | フューチャー技術ブログ"
  },
  {
   "path": "/articles/20240517a/",
   "pv": "221",
   "title": "OpenAPI 3.0.3 と 3.1.0 どっち使う？ | フューチャー技術ブログ"
  },
  {
   "path": "/articles/20240417a/",
   "pv": "218",
   "title": "謎のAIチップベンダーTenstorrent製のAIボードを使ってみる（開封編） | フューチャー技術ブログ"
  },
  {
   "path": "/articles/20230816a/",
   "pv": "209",
   "title": "Go1.21:slicesパッケージのチートシート | フューチャー技術ブログ"
  },
  {
   "path": "/articles/20240328b/",
   "pv": "206",
   "title": "Terraformでのループ処理と条件分岐 | フューチャー技術ブログ"
  },
  {
   "path": "/articles/20221116a/",
   "pv": "200",
   "title": "Plotly.pyによるデータ可視化のすすめ | フューチャー技術ブログ"
  },
  {
   "path": "/articles/20221012a/",
   "pv": "196",
   "title": "OAuth の仕組みを理解しながらクライアントを実装してみる | フューチャー技術ブログ"
  },
  {
   "path": "/articles/20230822a/",
   "pv": "196",
   "title": "Playwrightのインストール方法と使い方 | フューチャー技術ブログ"
  },
  {
   "path": "/articles/20210406/",
   "pv": "193",
   "title": "Bashのシェル展開 | フューチャー技術ブログ"
  }
 ],
 "weekly": [
  {
   "path": "/",
   "pv": "521",
   "title": "フューチャー技術ブログ"
  },
  {
   "path": "/articles/20240726a/",
   "pv": "425",
   "title": "2024年版のDockerfileの考え方＆書き方 | フューチャー技術ブログ"
  },
  {
   "path": "/articles/20200821/",
   "pv": "351",
   "title": "エンジニアが最低限理解しておくべきOSSライセンスの基礎知識 | フューチャー技術ブログ"
  },
  {
   "path": "/articles/20220922a/",
   "pv": "230",
   "title": "AGPLを理解する: もっとも誤解されたライセンス | フューチャー技術ブログ"
  },
  {
   "path": "/articles/20241113a/",
   "pv": "226",
   "title": "PostgreSQLで連番を自動生成するIDENTITY列。SERIALとどちらを使うべきか | フューチャー技術ブログ"
  },
  {
   "path": "/articles/20240419a/",
   "pv": "222",
   "title": "CI/CD初心者のためのJenkins入門 | フューチャー技術ブログ"
  },
  {
   "path": "/articles/20211026a/",
   "pv": "216",
   "title": "AWS利用時に read: connection reset by peer が出たときのリトライ検討 | フューチャー技術ブログ"
  },
  {
   "path": "/articles/20240415a/",
   "pv": "199",
   "title": "VSCodeでGitLensを使う | フューチャー技術ブログ"
  },
  {
   "path": "/articles/20230216a/",
   "pv": "188",
   "title": "Mac 慣れした私に Windows が支給されたので、まず設定したこと | フューチャー技術ブログ"
  },
  {
   "path": "/articles/20211201a/",
   "pv": "178",
   "title": "巡回セールスマン問題(TSP)の基本的な解き方(ILS) | フューチャー技術ブログ"
  },
  {
   "path": "/articles/20231101a/",
   "pv": "163",
   "title": "設計ドキュメント腐る問題、Git管理で運用してみた結果 | フューチャー技術ブログ"
  },
  {
   "path": "/articles/20200116/",
   "pv": "156",
   "title": "実践Drawio | フューチャー技術ブログ"
  },
  {
   "path": "/articles/20201223/",
   "pv": "141",
   "title": "2021年版Pythonの型ヒントの書き方 (for Python 3.9) | フューチャー技術ブログ"
  },
  {
   "path": "/articles/20211028b/",
   "pv": "135",
   "title": "OpenAPIにおけるundefinedとnullの設計 | フューチャー技術ブログ"
  },
  {
   "path": "/articles/20210621a/",
   "pv": "133",
   "title": "どうしてHTML5が廃止されたのか | フューチャー技術ブログ"
  },
  {
   "path": "/articles/20200810/",
   "pv": "127",
   "title": "自動売買ツールを自作してみよう | フューチャー技術ブログ"
  },
  {
   "path": "/articles/20241226a/",
   "pv": "124",
   "title": "Fast APIのすすめ（概要編） | フューチャー技術ブログ"
  },
  {
   "path": "/articles/20220530a/",
   "pv": "121",
   "title": "【エネルギー業界】LPガス基礎part2 供給設備編 | フューチャー技術ブログ"
  },
  {
   "path": "/articles/20200428/",
   "pv": "118",
   "title": "Vue.jsのslotの機能を初心者にわかるように解説してみた | フューチャー技術ブログ"
  },
  {
   "path": "/articles/20240705a/",
   "pv": "117",
   "title": "署名付きURLを利用したファイルアップロードWeb API設計の勘所 | フューチャー技術ブログ"
  },
  {
   "path": "/articles/20220628a/",
   "pv": "116",
   "title": "資料作成のポイント（定例、課題解決用） | フューチャー技術ブログ"
  },
  {
   "path": "/articles/20210823b/",
   "pv": "110",
   "title": "Wiresharkで通信プロトコルを見る | フューチャー技術ブログ"
  },
  {
   "path": "/articles/20210518a/",
   "pv": "108",
   "title": "HTTP検索条件、GETにするか？POSTにするか？ | フューチャー技術ブログ"
  },
  {
   "path": "/articles/20200828/",
   "pv": "104",
   "title": "チームで推奨するVSCode拡張機能を共有するtips | フューチャー技術ブログ"
  },
  {
   "path": "/articles/20210331/",
   "pv": "94",
   "title": "今さらながらfindパイセンについてまとめてみた | フューチャー技術ブログ"
  },
  {
   "path": "/articles/20240620a/",
   "pv": "93",
   "title": "個人的docker composeおすすめtips 9選 | フューチャー技術ブログ"
  },
  {
   "path": "/articles/20210204/",
   "pv": "87",
   "title": "JP1ジョブ設計のポイント（初級） | フューチャー技術ブログ"
  },
  {
   "path": "/articles/20210401/",
   "pv": "81",
   "title": "declare使ってBashで配列と連想配列 | フューチャー技術ブログ"
  },
  {
   "path": "/articles/20241205a/",
   "pv": "78",
   "title": "TypeScript/JavaScript Array完全攻略2024 | フューチャー技術ブログ"
  },
  {
   "path": "/articles/20250127a/",
   "pv": "78",
   "title": "Go 1.24連載始まります\u0026os.Root、WASMの最新のまとめ | フューチャー技術ブログ"
  },
  {
   "path": "/articles/20191107/",
   "pv": "77",
   "title": "インフラ入門vol.3(ネットワーク冗長化構成) | フューチャー技術ブログ"
  },
  {
   "path": "/articles/20200409/",
   "pv": "74",
   "title": "スキーマファースト開発のためのOpenAPI（Swagger）設計規約 | フューチャー技術ブログ"
  },
  {
   "path": "/articles/20210330/",
   "pv": "74",
   "title": "CSVと親しくなるAWK術 | フューチャー技術ブログ"
  },
  {
   "path": "/articles/20220621a/",
   "pv": "73",
   "title": "ファイルダウンロード完全マスター | フューチャー技術ブログ"
  },
  {
   "path": "/articles/20230816a/",
   "pv": "73",
   "title": "Go1.21:slicesパッケージのチートシート | フューチャー技術ブログ"
  },
  {
   "path": "/articles/20250109a/",
   "pv": "73",
   "title": "構造化テキスト(URL)を文字列結合で作らないようにするライブラリを作ってみた | フューチャー技術ブログ"
  },
  {
   "path": "/articles/20231128a/",
   "pv": "72",
   "title": "data-testidはいつ使うべきか？そもそも使うべきなのか？ | フューチャー技術ブログ"
  },
  {
   "path": "/articles/20240517a/",
   "pv": "69",
   "title": "OpenAPI 3.0.3 と 3.1.0 どっち使う？ | フューチャー技術ブログ"
  },
  {
   "path": "/articles/20241111a/",
   "pv": "69",
   "title": "フロントエンドフレームワークからサーバーにアクセスするパターン | フューチャー技術ブログ"
  },
  {
   "path": "/articles/20221118a/",
   "pv": "66",
   "title": "MSAL.jsを使ってウェブフロントエンドだけでAzureAD認証する | フューチャー技術ブログ"
  },
  {
   "path": "/articles/20220713a/",
   "pv": "65",
   "title": "【エネルギー業界】LPガス基礎part4 バルク配送入門 | フューチャー技術ブログ"
  },
  {
   "path": "/articles/20240328b/",
   "pv": "65",
   "title": "Terraformでのループ処理と条件分岐 | フューチャー技術ブログ"
  },
  {
   "path": "/articles/20220929a/",
   "pv": "63",
   "title": "AGPLが適する場所、適さない場所 | フューチャー技術ブログ"
  },
  {
   "path": "/articles/20221025a/",
   "pv": "63",
   "title": "A5:SQL Mk-2 （a5m2）のデータモデリング便利機能（初心者向け） | フューチャー技術ブログ"
  },
  {
   "path": "/articles/20230822a/",
   "pv": "61",
   "title": "Playwrightのインストール方法と使い方 | フューチャー技術ブログ"
  },
  {
   "path": "/articles/20241214a/",
   "pv": "59",
   "title": "Gitブランチフロー規約の紹介 | フューチャー技術ブログ"
  },
  {
   "path": "/articles/20221116a/",
   "pv": "58",
   "title": "Plotly.pyによるデータ可視化のすすめ | フューチャー技術ブログ"
  },
  {
   "path": "/articles/20231214a/",
   "pv": "58",
   "title": "React Server ComponentでもContextで状態を共有する | フューチャー技術ブログ"
  },
  {
   "path": "/articles/20241227a/",
   "pv": "57",
   "title": "新卒 2 年目社員の Software Design 寄稿 | フューチャー技術ブログ"
  },
  {
   "path": "/articles/20240417a/",
   "pv": "54",
   "title": "謎のAIチップベンダーTenstorrent製のAIボードを使ってみる（開封編） | フューチャー技術ブログ"
  }
 ],
 "yearly": [
  {
   "path": "/articles/20240726a/",
   "pv": "57654",
   "title": "2024年版のDockerfileの考え方＆書き方 | フューチャー技術ブログ"
  },
  {
   "path": "/",
   "pv": "37831",
   "title": "(not set)"
  },
  {
   "path": "/",
   "pv": "31761",
   "title": "フューチャー技術ブログ"
  },
  {
   "path": "/articles/20240215a/",
   "pv": "28426",
   "title": "龍が如く7のすごいテストをなぜ我々は採用できないのか | フューチャー技術ブログ"
  },
  {
   "path": "/articles/20200821/",
   "pv": "23558",
   "title": "エンジニアが最低限理解しておくべきOSSライセンスの基礎知識 | フューチャー技術ブログ"
  },
  {
   "path": "/articles/20211026a/",
   "pv": "19616",
   "title": "AWS利用時に read: connection reset by peer が出たときのリトライ検討 | フューチャー技術ブログ"
  },
  {
   "path": "/articles/20240410a/",
   "pv": "17164",
   "title": "2024年Gitワークフロー再考 | フューチャー技術ブログ"
  },
  {
   "path": "/articles/20240620a/",
   "pv": "14208",
   "title": "個人的docker composeおすすめtips 9選 | フューチャー技術ブログ"
  },
  {
   "path": "/articles/20210621a/",
   "pv": "14174",
   "title": "どうしてHTML5が廃止されたのか | フューチャー技術ブログ"
  },
  {
   "path": "/articles/20201223/",
   "pv": "13830",
   "title": "2021年版Pythonの型ヒントの書き方 (for Python 3.9) | フューチャー技術ブログ"
  },
  {
   "path": "/articles/20241111a/",
   "pv": "12912",
   "title": "フロントエンドフレームワークからサーバーにアクセスするパターン | フューチャー技術ブログ"
  },
  {
   "path": "/articles/20220922a/",
   "pv": "12888",
   "title": "AGPLを理解する: もっとも誤解されたライセンス | フューチャー技術ブログ"
  },
  {
   "path": "/articles/20230216a/",
   "pv": "10852",
   "title": "Mac 慣れした私に Windows が支給されたので、まず設定したこと | フューチャー技術ブログ"
  },
  {
   "path": "/articles/20240611a/",
   "pv": "10294",
   "title": "Gitのブランチの役割を考える | フューチャー技術ブログ"
  },
  {
   "path": "/articles/20240705a/",
   "pv": "9099",
   "title": "署名付きURLを利用したファイルアップロードWeb API設計の勘所 | フューチャー技術ブログ"
  },
  {
   "path": "/articles/20211201a/",
   "pv": "8126",
   "title": "巡回セールスマン問題(TSP)の基本的な解き方(ILS) | フューチャー技術ブログ"
  },
  {
   "path": "/articles/20231101a/",
   "pv": "8090",
   "title": "設計ドキュメント腐る問題、Git管理で運用してみた結果 | フューチャー技術ブログ"
  },
  {
   "path": "/articles/20200116/",
   "pv": "7406",
   "title": "実践Drawio | フューチャー技術ブログ"
  },
  {
   "path": "/articles/20210518a/",
   "pv": "7230",
   "title": "HTTP検索条件、GETにするか？POSTにするか？ | フューチャー技術ブログ"
  },
  {
   "path": "/articles/20211028b/",
   "pv": "7174",
   "title": "OpenAPIにおけるundefinedとnullの設計 | フューチャー技術ブログ"
  },
  {
   "path": "/articles/20200428/",
   "pv": "6917",
   "title": "Vue.jsのslotの機能を初心者にわかるように解説してみた | フューチャー技術ブログ"
  },
  {
   "path": "/articles/20240415a/",
   "pv": "6714",
   "title": "VSCodeでGitLensを使う | フューチャー技術ブログ"
  },
  {
   "path": "/articles/20200828/",
   "pv": "6447",
   "title": "チームで推奨するVSCode拡張機能を共有するtips | フューチャー技術ブログ"
  },
  {
   "path": "/articles/20220530a/",
   "pv": "6213",
   "title": "【エネルギー業界】LPガス基礎part2 供給設備編 | フューチャー技術ブログ"
  },
  {
   "path": "/articles/20221116a/",
   "pv": "5918",
   "title": "Plotly.pyによるデータ可視化のすすめ | フューチャー技術ブログ"
  },
  {
   "path": "/articles/20240402a/",
   "pv": "5894",
   "title": "Difyで生成AIアプリケーション入門　前編：生成AIアプリケーションをノーコードで開発 | フューチャー技術ブログ"
  },
  {
   "path": "/articles/20210823b/",
   "pv": "5711",
   "title": "Wiresharkで通信プロトコルを見る | フューチャー技術ブログ"
  },
  {
   "path": "/articles/20200810/",
   "pv": "5563",
   "title": "自動売買ツールを自作してみよう | フューチャー技術ブログ"
  },
  {
   "path": "/articles/20210120/",
   "pv": "5302",
   "title": "Androidのビルドバリアントをイチから理解する | フューチャー技術ブログ"
  },
  {
   "path": "/articles/20210401/",
   "pv": "5245",
   "title": "declare使ってBashで配列と連想配列 | フューチャー技術ブログ"
  },
  {
   "path": "/articles/20210331/",
   "pv": "5210",
   "title": "今さらながらfindパイセンについてまとめてみた | フューチャー技術ブログ"
  },
  {
   "path": "/articles/20220621a/",
   "pv": "5116",
   "title": "ファイルダウンロード完全マスター | フューチャー技術ブログ"
  },
  {
   "path": "/articles/20241214a/",
   "pv": "5010",
   "title": "Gitブランチフロー規約の紹介 | フューチャー技術ブログ"
  },
  {
   "path": "/articles/20210204/",
   "pv": "4967",
   "title": "JP1ジョブ設計のポイント（初級） | フューチャー技術ブログ"
  },
  {
   "path": "/articles/20220628a/",
   "pv": "4885",
   "title": "資料作成のポイント（定例、課題解決用） | フューチャー技術ブログ"
  },
  {
   "path": "/articles/20231128a/",
   "pv": "4867",
   "title": "data-testidはいつ使うべきか？そもそも使うべきなのか？ | フューチャー技術ブログ"
  },
  {
   "path": "/articles/20200409/",
   "pv": "4825",
   "title": "スキーマファースト開発のためのOpenAPI（Swagger）設計規約 | フューチャー技術ブログ"
  },
  {
   "path": "/articles/20240628a/",
   "pv": "4825",
   "title": "PostgreSQLのPub/Sub機能とJavaのクライアント実装 | フューチャー技術ブログ"
  },
  {
   "path": "/articles/20240419a/",
   "pv": "4733",
   "title": "CI/CD初心者のためのJenkins入門 | フューチャー技術ブログ"
  },
  {
   "path": "/articles/20240228a/",
   "pv": "4722",
   "title": "Next.jsにするか他のフレームワークにするか迷っている人はNext.jsを選べばいい | フューチャー技術ブログ"
  },
  {
   "path": "/articles/20191107/",
   "pv": "4655",
   "title": "インフラ入門vol.3(ネットワーク冗長化構成) | フューチャー技術ブログ"
  },
  {
   "path": "/articles/20241226a/",
   "pv": "4617",
   "title": "Fast APIのすすめ（概要編） | フューチャー技術ブログ"
  },
  {
   "path": "/articles/20241205a/",
   "pv": "4581",
   "title": "TypeScript/JavaScript Array完全攻略2024 | フューチャー技術ブログ"
  },
  {
   "path": "/articles/20240129a/",
   "pv": "4520",
   "title": "Go 1.22リリース連載始まります \u0026 ループの変化とTinyGo 0.31 | フューチャー技術ブログ"
  },
  {
   "path": "/articles/20200601/",
   "pv": "4490",
   "title": "Goのテストに入門してみよう！ | フューチャー技術ブログ"
  },
  {
   "path": "/articles/20220929a/",
   "pv": "4484",
   "title": "AGPLが適する場所、適さない場所 | フューチャー技術ブログ"
  },
  {
   "path": "/articles/20240208a/",
   "pv": "4253",
   "title": "ダイアログもアラートも、Reactで子コンポーネントの開閉管理を実装する | フューチャー技術ブログ"
  },
  {
   "path": "/articles/20191008/",
   "pv": "4179",
   "title": "本当に使ってよかったOpenAPI (Swagger) ツール | フューチャー技術ブログ"
  },
  {
   "path": "/articles/20230313a/",
   "pv": "4163",
   "title": "【エネルギー業界】国家資格「高圧ガス第二種販売主任者」合格までの道のり | フューチャー技術ブログ"
  },
  {
   "path": "/articles/20240404a/",
   "pv": "4108",
   "title": "Difyで生成AIアプリケーション入門　後編：自作プログラムで機能追加して生成AIの指向性と精度を高める | フューチャー技術ブログ"
  }
 ]
}
